Workbook
Name HDFC: Table7[[HDFC Bank ]]
Name HUL: Table7[HUL]
Name Infosys: Table7[Infosys]
Name Market: Table7[Market]
Name Maruti: Table7[Maruti]
Name PortfolioValue: 'Monte Carlo Simulation'!$C$11:$C$10010
Name Return: 'Monte Carlo Simulation'!$B$11:$B$10010
Name SunPharma: Table7[Sun Pharma]

Sheet Problem Statement
A1: Portfolio Analytics, Optimization and Risk Management of an Equity Portfolio Using Microsoft Excel
A3: Problem Statement
A5: The increasing volatility and uncertainty in financial markets make it essential for investors to adopt a systematic approach to portfolio construction and risk management.
A6: Investment decisions based solely on expected returns often ignore diversification, market risk, and potential losses during adverse market conditions.
A7: Consequently, investors require analytical tools that can optimize portfolio allocation, evaluate performance, quantify downside risk, and recommend appropriate hedging strategies.
A8: This project develops an integrated Portfolio Analytics, Optimization, and Risk Management Model using Microsoft Excel for a portfolio consisting of five selected Indian equities.
A9: The project applies quantitative finance techniques to evaluate historical performance, optimize portfolio allocation, simulate future outcomes, measure downside risk, and analyze hedging strategies.
A11: Scope of Work
A13: The project includes the following analyses:
A15: 1 | B15: Historical stock price collection and data preprocessing
A16: 2 | B16: Daily and annual return calculations
A17: 3 | B17: Descriptive statistical analysis (Mean, Median, Standard Deviation, Variance, Skewness and Kurtosis)
A18: 4 | B18: Correlation and Covariance Matrix analysis
A19: 5 | B19: Portfolio return and risk estimation
A20: 6 | B20: Beta estimation for individual stocks and the overall portfolio
A21: 7 | B21: CAPM-based expected return calculation
A22: 8 | B22: Alpha estimation to measure excess returns
A23: 9 | B23: Sharpe Ratio analysis for risk-adjusted performance evaluation
A24: 10 | B24: Portfolio optimization using Modern Portfolio Theory (MPT) and Microsoft Excel Solver
A25: 11 | B25: Monte Carlo Simulation (10,000 simulations) to estimate future portfolio performance
A26: 12 | B26: Parametric and Monte Carlo Value at Risk (VaR) estimation at 95% and 99% confidence levels
... A29: 15 | B29: Executive summary and investment insights based on the analytical findings
A31: Objective
A33: The primary objective of this project is to design an optimized equity portfolio that maximizes risk-adjusted returns while effectively managing downside risk.
A34: By integrating portfolio optimization, simulation techniques, statistical analysis, and hedging strategies into a single Excel-based framework, the project demonstrates
A35: how quantitative financial tools can support informed investment decisions and improve portfolio resilience under varying market conditions.

Sheet Returns
B1: Returns Calculation
B4: Market | C4: Maruti | D4: Sun Pharma | E4: HUL | F4: Infosys | G4: HDFC Bank | I4: CAGR Returns (5 yrs)
B5: -0.0002 | C5: 0.0147 | D5: -0.0007 | E5: -0.002 | F5: 0.0057 | G5: -0.0088
B6: 0.0011 | C6: 0.007 | D6: 0.0046 | E6: -0.0083 | F6: -0.0152 | G6: 0.0075 | I6: Market | J6: =(('Nifty 50'!B2/'Nifty 50'!B1240)^(1/5)-1) -> 0.086170442
B7: -0.0066 | C7: -0.015 | D7: 0.011 | E7: -0.0049 | F7: -0.0088 | G7: -0.0105 | I7: Maruti | J7: =(Maruti!B2/Maruti!B1240)^(1/5)-1 -> 0.13543414
B8: 0.0002 | C8: -0.0115 | D8: -0.0073 | E8: -0.0093 | F8: 0.0324 | G8: -0.0085 | I8: Sun Pharma | J8: =('Sun Pharma'!B2/'Sun Pharma'!B1240)^(1/5)-1 -> 0.23145337
B9: 0.0102 | C9: 0.0092 | D9: -0.0017 | E9: 0.0028 | F9: 0.0164 | G9: 0.0091 | I9: HUL | J9: =(HUL!B2/HUL!B1240)^(1/5)-1 -> -0.027906695
B10: 0.0034 | C10: -0.016 | D10: 0.0267 | E10: 0.0041 | F10: -0.0173 | G10: 0.0089 | I10: Infosys | J10: =(Infosys!B2/Infosys!B1240)^(1/5)-1 -> -0.069949896
B11: -0.0212 | C11: -0.0404 | D11: -0.008 | E11: -0.033 | F11: -0.0023 | G11: -0.0229 | I11: HDFC Bank | J11: =('HDFC Bank'!B2/'HDFC Bank'!B1240)^(1/5)-1 -> 0.012588474
B12: -0.0013 | C12: 0.0057 | D12: -0.0049 | E12: 0.0031 | F12: 0.0284 | G12: -0.0007 | I12: Risk free rate | J12: 0.0675
B13: 0.0066 | C13: 0.0063 | D13: 0.0042 | E13: 0.0004 | F13: -0.0048 | G13: 0.036
B14: 0.0039 | C14: 0.0013 | D14: 0.0181 | E14: -0.0043 | F14: 0.0061 | G14: 0.0065
B15: 0.0071 | C15: -0.0033 | D15: 0.0026 | E15: 0.0131 | F15: 0.0564 | G15: -0.0003
B16: 0.0059 | C16: 0.0198 | D16: 0.002 | E16: 0.0301 | F16: -0.0151 | G16: -0.0023
B17: -0.0034 | C17: 0.0524 | D17: -0.0066 | E17: -0.0154 | F17: -0.035 | G17: -0.0012
B18: -0.0046 | C18: -0.0242 | D18: 0.0064 | E18: -0.0105 | F18: -0.0043 | G18: 0.0033
B19: 0.0014 | C19: 0.0375 | D19: -0.0062 | E19: 0.0076 | F19: -0.0146 | G19: 0.0039
B20: 0.0083 | C20: -0.0151 | D20: 0.0034 | E20: -0.0011 | F20: 0.0265 | G20: 0.0239
B21: -0.0116 | C21: 0.0022 | D21: 0.0027 | E21: -0.0114 | F21: -0.0339 | G21: -0.0149
B22: 0.0037 | C22: 0.0019 | D22: 0.0134 | E22: -0.0044 | F22: 0.0133 | G22: 0.0085
B23: -0.0064 | C23: -0.0066 | D23: 0.0074 | E23: -0.0108 | F23: -0.0675 | G23: -0.024
B24: 0.0034 | C24: -0.0107 | D24: 0.0024 | E24: 0.0095 | F24: -0.0261 | G24: 0.0151
... B1243: -0.0001 | C1243: -0.0005 | D1243: 0.0082 | E1243: 0.0021 | F1243: -0.016 | G1243: 0.0011

Sheet Statistics
A1: Statistical Summary
A3: Statistics | B3: Market | C3: Maruti | D3: Sun Pharma | E3: HUL | F3: Infosys | G3: HDFC Bank
A4: Mean | B4: 0.00037304278 | C4: 0.00062001614 | D4: 0.00093075061 | E4: -3.1557708e-05 | F4: -0.00017522195 | G4: 0.00013712672
A5: Standard Error | B5: 0.00024764641 | C5: 0.00042183372 | D5: 0.00036862112 | E5: 0.00036050201 | F5: 0.00045928986 | G5: 0.0003744103
A6: Median | B6: 0.0005 | C6: 0.0002 | D6: 0.0006 | E6: -0.0004 | F6: -0.0002 | G6: 0.0004
A7: Mode | B7: 0.0014 | C7: -0.0018 | D7: -0.0015 | E7: -0.001 | F7: -0.0027 | G7: 0.0065
A8: Standard Deviation (Annualised) | B8: =0.871701304001829%*SQRT(252) -> 0.13837829 | C8: =1.484830738872%*SQRT(252) -> 0.23570957 | D8: =1.29752541413983%*SQRT(252) -> 0.20597577 | E8: =1.2689466078155%*SQRT(252) -> 0.20143903 | F8: =1.61667419564937%*SQRT(252) -> 0.25663907 | G8: =1.31790298307106%*SQRT(252) -> 0.20921061
A9: Standard Deviation (Daily) | B9: =B8/SQRT(252) -> 0.008717013 | C9: =C8/SQRT(252) -> 0.014848307 | D9: =D8/SQRT(252) -> 0.012975254 | E9: =E8/SQRT(252) -> 0.012689466 | F9: =F8/SQRT(252) -> 0.016166742 | G9: =G8/SQRT(252) -> 0.01317903
A10: Sample Variance | B10: 7.5986316e-05 | C10: 0.00022047223 | D10: 0.00016835722 | E10: 0.00016102255 | F10: 0.00026136355 | G10: 0.00017368683
A11: Kurtosis | B11: 3.7349877 | C11: 3.8193864 | D11: 4.5899239 | E11: 2.304038 | F11: 3.6255004 | G11: 5.6180531
A12: Skewness | B12: -0.39514263 | C12: 0.42456634 | D12: 0.64015946 | E12: 0.22424626 | F12: -0.23779929 | G12: -0.071208586
A13: Range | B13: 0.0975 | C13: 0.1535 | D13: 0.1464 | E13: 0.1176 | F13: 0.1735 | G13: 0.1845
A14: Minimum | B14: -0.0593 | C14: -0.066 | D14: -0.0455 | E14: -0.058 | F14: -0.0942 | G14: -0.0844
A15: Maximum | B15: 0.0382 | C15: 0.0875 | D15: 0.1009 | E15: 0.0596 | F15: 0.0793 | G15: 0.1001
A16: Sum | B16: 0.4622 | C16: 0.7682 | D16: 1.1532 | E16: -0.0391 | F16: -0.2171 | G16: 0.1699
A17: Count | B17: 1239 | C17: 1239 | D17: 1239 | E17: 1239 | F17: 1239 | G17: 1239

Sheet Correlation & Covariance
B2: Correlation Matrix
B4: Particulars | C4: Market | D4: Maruti | E4: Sun Pharma | F4: HUL | G4: Infosys | H4: HDFC Bank
B5: Market | C5: 1 | D5: 0.51236599 | E5: 0.38301643 | F5: 0.37043133 | G5: 0.51310908 | H5: 0.70305388
B6: Maruti | C6: 0.51236599 | D6: 1 | E6: 0.1742077 | F6: 0.28356529 | G6: 0.13848171 | H6: 0.30959183
B7: Sun Pharma | C7: 0.38301643 | D7: 0.1742077 | E7: 1 | F7: 0.1466767 | G7: 0.19215707 | H7: 0.16541624
B8: HUL | C8: 0.37043133 | D8: 0.28356529 | E8: 0.1466767 | F8: 1 | G8: 0.19056642 | H8: 0.21165572
B9: Infosys | C9: 0.51310908 | D9: 0.13848171 | E9: 0.19215707 | F9: 0.19056642 | G9: 1 | H9: 0.24570263
B10: HDFC Bank | C10: 0.70305388 | D10: 0.30959183 | E10: 0.16541624 | F10: 0.21165572 | G10: 0.24570263 | H10: 1
B12: Covariance Matrix
B14: Particulars | C14: Market | D14: Maruti | E14: Sun Pharma | F14: HUL | G14: Infosys | H14: HDFC Bank
B15: Market | C15: =VARP(Returns!$B$5:$B$1243) -> 7.5924988e-05 | D15: 6.6263486e-05 | E15: 4.3286285e-05 | F15: 4.094191e-05 | G15: 7.2251895e-05 | H15: 8.0702889e-05
B16: Maruti | C16: 6.6263486e-05 | D16: =VARP(Returns!$C$5:$C$1243) -> 0.00022029429 | E16: 3.3535866e-05 | F16: 5.3385426e-05 | G16: 3.3215533e-05 | H16: 6.0533978e-05
B17: Sun Pharma | C17: 4.3286285e-05 | D17: 3.3535866e-05 | E17: =VARP(Returns!$D$5:$D$1243) -> 0.00016822134 | F17: 2.4130688e-05 | G17: 4.0275792e-05 | H17: 2.8263556e-05
B18: HUL | C18: 4.094191e-05 | D18: 5.3385426e-05 | E18: 2.4130688e-05 | F18: =VARP(Returns!$E$5:$E$1243) -> 0.00016089259 | G18: 3.9062638e-05 | H18: 3.5367645e-05
B19: Infosys | C19: 7.2251895e-05 | D19: 3.3215533e-05 | E19: 4.0275792e-05 | F19: 3.9062638e-05 | G19: =VARP(Returns!$F$5:$F$1243) -> 0.0002611526 | H19: 5.2307635e-05
B20: HDFC Bank | C20: 8.0702889e-05 | D20: 6.0533978e-05 | E20: 2.8263556e-05 | F20: 3.5367645e-05 | G20: 5.2307635e-05 | H20: =VARP(Returns!$G$5:$G$1243) -> 0.00017354664

Sheet Performance Metrics
B1: Individual Performance Metrics
B3: Particulas | C3: Maruti | D3: Sun Pharma | E3: HUL | F3: Infosys | G3: HDFC Bank
B4: Covariance with Market | C4: =_xlfn.COVARIANCE.P(Market,Maruti) -> 6.6263486e-05 | D4: =_xlfn.COVARIANCE.P(Market,SunPharma) -> 4.3286285e-05 | E4: =_xlfn.COVARIANCE.P(Market,HUL) -> 4.094191e-05 | F4: =_xlfn.COVARIANCE.P(Market,Infosys) -> 7.2251895e-05 | G4: =_xlfn.COVARIANCE.P(Market,HDFC) -> 8.0702889e-05
B5: Variance of Market | C5: =_xlfn.VAR.S(Market) -> 7.5986316e-05 | D5: =C5 -> 7.5986316e-05 | E5: =D5 -> 7.5986316e-05 | F5: =E5 -> 7.5986316e-05 | G5: =F5 -> 7.5986316e-05
B6: Beta of the stocks | C6: =C4/C5 -> 0.87204498 | D6: =D4/D5 -> 0.56965895 | E6: =E4/E5 -> 0.53880635 | F6: =F4/F5 -> 0.95085403 | G6: =G4/G5 -> 1.0620713
B8: Cost of Equity (CAPM) | C8: =Returns!$J$12+(Returns!$J$6-Returns!$J$12)*'Performance Metrics'!C6 -> 0.083781465 | D8: =Returns!$J$12+(Returns!$J$6-Returns!$J$12)*'Performance Metrics'!D6 -> 0.078135784 | E8: =Returns!$J$12+(Returns!$J$6-Returns!$J$12)*'Performance Metrics'!E6 -> 0.077559753 | F8: =Returns!$J$12+(Returns!$J$6-Returns!$J$12)*'Performance Metrics'!F6 -> 0.085252865 | G8: =Returns!$J$12+(Returns!$J$6-Returns!$J$12)*'Performance Metrics'!G6 -> 0.087329342
B9: Actual returns | C9: 0.13543414 | D9: 0.23145337 | E9: -0.027906695 | F9: -0.069949896 | G9: 0.012588474
B10: Alpha | C10: =C9-C8 -> 0.051652679 | D10: =D9-D8 -> 0.15331759 | E10: =E9-E8 -> -0.10546645 | F10: =F9-F8 -> -0.15520276 | G10: =G9-G8 -> -0.074740867
B11: Sharpe | C11: =(C9-Returns!$J$12)/Statistics!C8 -> 0.28821122 | D11: =(D9-Returns!$J$12)/Statistics!D8 -> 0.79598377 | E11: =(E9-Returns!$J$12)/Statistics!E8 -> -0.47362567 | F11: =(F9-Returns!$J$12)/Statistics!F8 -> -0.53557666 | G11: =(G9-Returns!$J$12)/Statistics!G8 -> -0.26247008

Sheet Portfolio Optimizer
B1: Portfolio Optimizer
B3: Investment | C3: 100000000 | D3: (enter investment amount here)
B5: Security | C5: Maruti | D5: Sun Pharma | E5: HUL | F5: Infosys | G5: HDFC Bank
B6: Annual Return | C6: ='Performance Metrics'!C9 -> 0.13543414 | D6: ='Performance Metrics'!D9 -> 0.23145337 | E6: ='Performance Metrics'!E9 -> -0.027906695 | F6: ='Performance Metrics'!F9 -> -0.069949896 | G6: ='Performance Metrics'!G9 -> 0.012588474
B7: Standard deviation | C7: =Statistics!C8 -> 0.23570957 | D7: =Statistics!D8 -> 0.20597577 | E7: =Statistics!E8 -> 0.20143903 | F7: =Statistics!F8 -> 0.25663907 | G7: =Statistics!G8 -> 0.20921061
B8: Minimum Weight | C8: 0.05 | D8: 0.05 | E8: 0.05 | F8: 0.05 | G8: 0.05
B9: Maximum Weight | C9: 0.25 | D9: 0.25 | E9: 0.25 | F9: 0.25 | G9: 0.25
B10: Optimal Weight | C10: 0.25 | D10: 0.25 | E10: 0.2 | F10: 0.05 | G10: 0.25
B11: Investment | C11: =$C$3*C10 -> 25000000 | D11: =$C$3*D10 -> 25000000 | E11: =$C$3*E10 -> 20000000 | F11: =$C$3*F10 -> 5000000 | G11: =$C$3*G10 -> 25000000
B14: Portfolio Summary
B15: Expected Return | C15: =SUMPRODUCT(C6:G6,C10:G10) -> 0.085790164
B16: Standard Deviation | C16: {=SQRT(MMULT(MMULT(C10:G10,'Correlation & Covariance'!D16:H20),TRANSPOSE(C10:G10)*252))} -> 0.13537498
B17: Risk free rate | C17: =Returns!J12 -> 0.0675
B18: Total Weight | C18: =SUM(C10:G10) -> 1
B19: Sharpe | C19: =(C15-C17)/C16 -> 0.13510741
B20: Portfolio Alpha | C20: =SUMPRODUCT(C10:G10,'Performance Metrics'!C10:G10) -> 0.0037039225
B21: Portfolio Beta | C21: =SUMPRODUCT(C10:G10,'Performance Metrics'!C6:G6) -> 0.78124779

Sheet Efficient Frontier
A1: Portfolio | B1: Random Numbers | G1: Weights | L1: Risk & Return
B2: Maruti | C2: Sun Pharma | D2: HUL | E2: Infosys | F2: HDFC Bank | G2: Maruti | H2: Sun Pharma | I2: HUL | J2: Infosys | K2: HDFC Bank | L2: Volatility | M2: Exp return
A3: 1 | B3: =RAND() -> 0.51935209 | C3: =RAND() -> 0.68865022 | D3: =RAND() -> 0.41068978 | E3: =RAND() -> 0.43730741 | F3: =RAND() -> 0.26129634 | G3: =B3/SUM($B3:$F3) -> 0.22411989 | H3: =C3/SUM($B3:$F3) -> 0.29717838 | I3: =D3/SUM($B3:$F3) -> 0.17722803 | J3: =E3/SUM($B3:$F3) -> 0.18871454 | K3: =F3/SUM($B3:$F3) -> 0.11275916 | L3: {=SQRT(MMULT(MMULT(G3:K3,'Correlation & Covariance'!$D$16:$H$20),TRANSPOSE(G3:K3)*252))} -> 0.13494833 | M3: =SUMPRODUCT(G3:K3,'Performance Metrics'!$C$9:$G$9) -> 0.082409479
A4: 2 | B4: =RAND() -> 0.58382446 | C4: =RAND() -> 0.029397049 | D4: =RAND() -> 0.70312286 | E4: =RAND() -> 0.39407183 | F4: =RAND() -> 0.30100153 | G4: =B4/SUM($B4:$F4) -> 0.2902552 | H4: =C4/SUM($B4:$F4) -> 0.014615089 | I4: =D4/SUM($B4:$F4) -> 0.34956581 | J4: =E4/SUM($B4:$F4) -> 0.19591745 | K4: =F4/SUM($B4:$F4) -> 0.14964645 | L4: {=SQRT(MMULT(MMULT(G4:K4,'Correlation & Covariance'!$D$16:$H$20),TRANSPOSE(G4:K4)*252))} -> 0.14638939 | M4: =SUMPRODUCT(G4:K4,'Performance Metrics'!$C$9:$G$9) -> 0.021117365
A5: 3 | B5: =RAND() -> 0.168117 | C5: =RAND() -> 0.090946327 | D5: =RAND() -> 0.71522536 | E5: =RAND() -> 0.17922825 | F5: =RAND() -> 0.025433376 | G5: =B5/SUM($B5:$F5) -> 0.14259889 | H5: =C5/SUM($B5:$F5) -> 0.077141781 | I5: =D5/SUM($B5:$F5) -> 0.60666285 | J5: =E5/SUM($B5:$F5) -> 0.15202358 | K5: =F5/SUM($B5:$F5) -> 0.021572899 | L5: {=SQRT(MMULT(MMULT(G5:K5,'Correlation & Covariance'!$D$16:$H$20),TRANSPOSE(G5:K5)*252))} -> 0.15421191 | M5: =SUMPRODUCT(G5:K5,'Performance Metrics'!$C$9:$G$9) -> 0.0098750645
A6: 4 | B6: =RAND() -> 0.594498 | C6: =RAND() -> 0.21037432 | D6: =RAND() -> 0.9398776 | E6: =RAND() -> 0.41743432 | F6: =RAND() -> 0.12838208 | G6: =B6/SUM($B6:$F6) -> 0.25954193 | H6: =C6/SUM($B6:$F6) -> 0.091843803 | I6: =D6/SUM($B6:$F6) -> 0.41032542 | J6: =E6/SUM($B6:$F6) -> 0.18224066 | K6: =F6/SUM($B6:$F6) -> 0.056048183 | L6: {=SQRT(MMULT(MMULT(G6:K6,'Correlation & Covariance'!$D$16:$H$20),TRANSPOSE(G6:K6)*252))} -> 0.14412984 | M6: =SUMPRODUCT(G6:K6,'Performance Metrics'!$C$9:$G$9) -> 0.032915416
A7: 5 | B7: =RAND() -> 0.60311602 | C7: =RAND() -> 0.10975894 | D7: =RAND() -> 0.63410628 | E7: =RAND() -> 0.71287561 | F7: =RAND() -> 0.95208963 | G7: =B7/SUM($B7:$F7) -> 0.20024128 | H7: =C7/SUM($B7:$F7) -> 0.036441199 | I7: =D7/SUM($B7:$F7) -> 0.2105304 | J7: =E7/SUM($B7:$F7) -> 0.23668269 | K7: =F7/SUM($B7:$F7) -> 0.31610443 | L7: {=SQRT(MMULT(MMULT(G7:K7,'Correlation & Covariance'!$D$16:$H$20),TRANSPOSE(G7:K7)*252))} -> 0.1438408 | M7: =SUMPRODUCT(G7:K7,'Performance Metrics'!$C$9:$G$9) -> 0.01710208
A8: 6 | B8: =RAND() -> 0.82103863 | C8: =RAND() -> 0.75044022 | D8: =RAND() -> 0.57573065 | E8: =RAND() -> 0.2475909 | F8: =RAND() -> 0.44533544 | G8: =B8/SUM($B8:$F8) -> 0.28908428 | H8: =C8/SUM($B8:$F8) -> 0.26422688 | I8: =D8/SUM($B8:$F8) -> 0.20271237 | J8: =E8/SUM($B8:$F8) -> 0.087175724 | K8: =F8/SUM($B8:$F8) -> 0.15680075 | L8: {=SQRT(MMULT(MMULT(G8:K8,'Correlation & Covariance'!$D$16:$H$20),TRANSPOSE(G8:K8)*252))} -> 0.13600373 | M8: =SUMPRODUCT(G8:K8,'Performance Metrics'!$C$9:$G$9) -> 0.090527001
A9: 7 | B9: =RAND() -> 0.81808425 | C9: =RAND() -> 0.15693353 | D9: =RAND() -> 0.73463912 | E9: =RAND() -> 0.3128191 | F9: =RAND() -> 0.45150207 | G9: =B9/SUM($B9:$F9) -> 0.33067563 | H9: =C9/SUM($B9:$F9) -> 0.063433678 | I9: =D9/SUM($B9:$F9) -> 0.2969465 | J9: =E9/SUM($B9:$F9) -> 0.12644376 | K9: =F9/SUM($B9:$F9) -> 0.18250043 | L9: {=SQRT(MMULT(MMULT(G9:K9,'Correlation & Covariance'!$D$16:$H$20),TRANSPOSE(G9:K9)*252))} -> 0.14398901 | M9: =SUMPRODUCT(G9:K9,'Performance Metrics'!$C$9:$G$9) -> 0.044632588
A10: 8 | B10: =RAND() -> 0.96928359 | C10: =RAND() -> 0.21723859 | D10: =RAND() -> 0.68303556 | E10: =RAND() -> 0.8704495 | F10: =RAND() -> 0.73277662 | G10: =B10/SUM($B10:$F10) -> 0.27910853 | H10: =C10/SUM($B10:$F10) -> 0.062554596 | I10: =D10/SUM($B10:$F10) -> 0.19668243 | J10: =E10/SUM($B10:$F10) -> 0.25064891 | K10: =F10/SUM($B10:$F10) -> 0.21100554 | L10: {=SQRT(MMULT(MMULT(G10:K10,'Correlation & Covariance'!$D$16:$H$20),TRANSPOSE(G10:K10)*252))} -> 0.1436708 | M10: =SUMPRODUCT(G10:K10,'Performance Metrics'!$C$9:$G$9) -> 0.031913913
A11: 9 | B11: =RAND() -> 0.8762371 | C11: =RAND() -> 0.58712492 | D11: =RAND() -> 0.40780969 | E11: =RAND() -> 0.93029102 | F11: =RAND() -> 0.97234009 | G11: =B11/SUM($B11:$F11) -> 0.23218942 | H11: =C11/SUM($B11:$F11) -> 0.15557912 | I11: =D11/SUM($B11:$F11) -> 0.10806333 | J11: =E11/SUM($B11:$F11) -> 0.24651288 | K11: =F11/SUM($B11:$F11) -> 0.25765525 | L11: {=SQRT(MMULT(MMULT(G11:K11,'Correlation & Covariance'!$D$16:$H$20),TRANSPOSE(G11:K11)*252))} -> 0.14040392 | M11: =SUMPRODUCT(G11:K11,'Performance Metrics'!$C$9:$G$9) -> 0.050439933
A12: 10 | B12: =RAND() -> 0.29386474 | C12: =RAND() -> 0.19914811 | D12: =RAND() -> 0.76852768 | E12: =RAND() -> 0.67799162 | F12: =RAND() -> 0.77966129 | G12: =B12/SUM($B12:$F12) -> 0.10807055 | H12: =C12/SUM($B12:$F12) -> 0.073237935 | I12: =D12/SUM($B12:$F12) -> 0.28263075 | J12: =E12/SUM($B12:$F12) -> 0.24933556 | K12: =F12/SUM($B12:$F12) -> 0.2867252 | L12: {=SQRT(MMULT(MMULT(G12:K12,'Correlation & Covariance'!$D$16:$H$20),TRANSPOSE(G12:K12)*252))} -> 0.14068203 | M12: =SUMPRODUCT(G12:K12,'Performance Metrics'!$C$9:$G$9) -> 0.0098687562
A13: 11 | B13: =RAND() -> 0.71963041 | C13: =RAND() -> 0.21216167 | D13: =RAND() -> 0.53501702 | E13: =RAND() -> 0.46707978 | F13: =RAND() -> 0.16235009 | G13: =B13/SUM($B13:$F13) -> 0.34329598 | H13: =C13/SUM($B13:$F13) -> 0.10121063 | I13: =D13/SUM($B13:$F13) -> 0.25522711 | J13: =E13/SUM($B13:$F13) -> 0.222818 | K13: =F13/SUM($B13:$F13) -> 0.077448274 | L13: {=SQRT(MMULT(MMULT(G13:K13,'Correlation & Covariance'!$D$16:$H$20),TRANSPOSE(G13:K13)*252))} -> 0.14489468 | M13: =SUMPRODUCT(G13:K13,'Performance Metrics'!$C$9:$G$9) -> 0.048185853
A14: 12 | B14: =RAND() -> 0.74427889 | C14: =RAND() -> 0.99314873 | D14: =RAND() -> 0.36634016 | E14: =RAND() -> 0.37642489 | F14: =RAND() -> 0.54615223 | G14: =B14/SUM($B14:$F14) -> 0.24593327 | H14: =C14/SUM($B14:$F14) -> 0.32816773 | I14: =D14/SUM($B14:$F14) -> 0.12105037 | J14: =E14/SUM($B14:$F14) -> 0.12438268 | K14: =F14/SUM($B14:$F14) -> 0.18046596 | L14: {=SQRT(MMULT(MMULT(G14:K14,'Correlation & Covariance'!$D$16:$H$20),TRANSPOSE(G14:K14)*252))} -> 0.13573437 | M14: =SUMPRODUCT(G14:K14,'Performance Metrics'!$C$9:$G$9) -> 0.099456409
... A102: 100 | B102: =RAND() -> 0.12186866 | C102: =RAND() -> 0.48817479 | D102: =RAND() -> 0.58698584 | E102: =RAND() -> 0.66189149 | F102: =RAND() -> 0.77847171 | G102: =B102/SUM($B102:$F102) -> 0.046208012 | H102: =C102/SUM($B102:$F102) -> 0.18509751 | I102: =D102/SUM($B102:$F102) -> 0.22256295 | J102: =E102/SUM($B102:$F102) -> 0.25096435 | K102: =F102/SUM($B102:$F102) -> 0.29516718 | L102: {=SQRT(MMULT(MMULT(G102:K102,'Correlation & Covariance'!$D$16:$H$20),TRANSPOSE(G102:K102)*252))} -> 0.13788316 | M102: =SUMPRODUCT(G102:K102,'Performance Metrics'!$C$9:$G$9) -> 0.029049364

Sheet Monte Carlo Simulation
A1: Monte Carlo Simulation (Yearly)
A3: Input | B3: Value | K3: Metric | L3: Value / % | N3: Return Range | O3: No of times | P3: % of times
A4: Initial Investment | B4: ='Portfolio Optimizer'!C3 -> 100000000 | K4: Number of Simulations | L4: =COUNT(B11:B10010) -> 10000 | N4: Below -50% | O4: =COUNTIF($B$11:$B$10010,"<-50%") -> 0 | P4: =O4/$O$26 -> 0
A5: Expected Return | B5: ='Portfolio Optimizer'!C15 -> 0.085790164 | K5: Average Simulated Return | L5: =AVERAGE(B11:B10010) -> 0.086473032 | N5: -50% to -45% | O5: =COUNTIFS($B$11:$B$10010,">=-50%",$B$11:$B$10010,"<-45%") -> 1 | P5: =O5/$O$26 -> 0.0001
A6: Portfolio Std Dev | B6: ='Portfolio Optimizer'!C16 -> 0.13537498 | K6: Median Return | L6: =MEDIAN(B11:B10010) -> 0.087636892 | N6: -45% to -40% | O6: =COUNTIFS($B$11:$B$10010,">=-45%",$B$11:$B$10010,"<-40%") -> 2 | P6: =O6/$O$26 -> 0.0002
A7: Simulations | B7: 10000 | K7: Standard Deviation | L7: =_xlfn.STDEV.S(B11:B10010) -> 0.13644932 | N7: -40% to -35% | O7: =COUNTIFS($B$11:$B$10010,">=-40%",$B$11:$B$10010,"<-35%") -> 4 | P7: =O7/$O$26 -> 0.0004
A8: Days | B8: 252 | K8: Minimum Return | L8: =MIN(B11:B10010) -> -0.45955914 | N8: -35% to -30% | O8: =COUNTIFS($B$11:$B$10010,">=-35%",$B$11:$B$10010,"<-30%") -> 19 | P8: =O8/$O$26 -> 0.0019
K9: Maximum Return | L9: =MAX(B11:B10010) -> 0.63675798 | N9: -30% to -25% | O9: =COUNTIFS($B$11:$B$10010,">=-30%",$B$11:$B$10010,"<-25%") -> 43 | P9: =O9/$O$26 -> 0.0043
A10: Iternations | B10: Return | C10: Portfolio Value (₹) | K10: 5th Percentile | L10: =_xlfn.PERCENTILE.INC(B11:B10010,0.05) -> -0.1399394 | N10: -25% to -20% | O10: =COUNTIFS($B$11:$B$10010,">=-25%",$B$11:$B$10010,"<-20%") -> 113 | P10: =O10/$O$26 -> 0.0113
A11: 1 | B11: 0.10521215 | C11: =$B$4*(1+B11) -> 1.1052121e+08 | K11: 95th Percentile | L11: =_xlfn.PERCENTILE.INC(B11:B10010,0.95) -> 0.30980714 | N11: -20% to -15% | O11: =COUNTIFS($B$11:$B$10010,">=-20%",$B$11:$B$10010,"<-15%") -> 241 | P11: =O11/$O$26 -> 0.0241
A12: 2 | B12: 0.1598598 | C12: =$B$4*(1+B12) -> 1.1598598e+08 | N12: -15% to -10% | O12: =COUNTIFS($B$11:$B$10010,">=-15%",$B$11:$B$10010,"<-10%") -> 443 | P12: =O12/$O$26 -> 0.0443
A13: 3 | B13: 0.0053485433 | C13: =$B$4*(1+B13) -> 1.0053485e+08 | K13: Metric | L13: Value / % | N13: -10% to -5% | O13: =COUNTIFS($B$11:$B$10010,">=-10%",$B$11:$B$10010,"<-5%") -> 712 | P13: =O13/$O$26 -> 0.0712
A14: 4 | B14: 0.13536594 | C14: =$B$4*(1+B14) -> 1.1353659e+08 | K14: Probability of Positive | L14: =COUNTIF(B9:B10008,">0")/COUNT(B9:B10008) -> 0.73434687 | N14: -5% to 0% | O14: =COUNTIFS($B$11:$B$10010,">=-5%",$B$11:$B$10010,"<0%") -> 1079 | P14: =O14/$O$26 -> 0.1079
A15: 5 | B15: -0.014283005 | C15: =$B$4*(1+B15) -> 98571699 | K15: Probability of Negative | L15: =COUNTIF(B9:B10008,"<0")/COUNT(B9:B10008) -> 0.26565313 | N15: 0% to 5% | O15: =COUNTIFS($B$11:$B$10010,">=0%",$B$11:$B$10010,"<5%") -> 1273 | P15: =O15/$O$26 -> 0.1273
A16: 6 | B16: -0.098449093 | C16: =$B$4*(1+B16) -> 90155091 | K16: Probability of Return >10% | L16: =COUNTIF(B11:B10010,">10%")/COUNT(B11:B10010) -> 0.4667 | N16: 5% to 10% | O16: =COUNTIFS($B$11:$B$10010,">=5%",$B$11:$B$10010,"<10%") -> 1403 | P16: =O16/$O$26 -> 0.1403
A17: 7 | B17: 0.14216646 | C17: =$B$4*(1+B17) -> 1.1421665e+08 | K17: Probability of Return >20% | L17: =COUNTIF(B11:B10010,">20%")/COUNT(B11:B10010) -> 0.2044 | N17: 10% to 15% | O17: =COUNTIFS($B$11:$B$10010,">=10%",$B$11:$B$10010,"<15%") -> 1448 | P17: =O17/$O$26 -> 0.1448
A18: 8 | B18: 0.036771117 | C18: =$B$4*(1+B18) -> 1.0367711e+08 | K18: Probability of Return >30% | L18: =COUNTIF(B11:B10010,">30%")/COUNT(B11:B10010) -> 0.0574 | N18: 15% to 20% | O18: =COUNTIFS($B$11:$B$10010,">=15%",$B$11:$B$10010,"<20%") -> 1175 | P18: =O18/$O$26 -> 0.1175
A19: 9 | B19: 0.23861482 | C19: =$B$4*(1+B19) -> 1.2386148e+08 | K19: Probability of Loss >10% | L19: =COUNTIF(B11:B10010,"<-10%")/COUNT(B11:B10010) -> 0.0866 | N19: 20% to 25% | O19: =COUNTIFS($B$11:$B$10010,">=20%",$B$11:$B$10010,"<25%") -> 885 | P19: =O19/$O$26 -> 0.0885
A20: 10 | B20: 0.2352899 | C20: =$B$4*(1+B20) -> 1.2352899e+08 | K20: Probability of Loss >20% | L20: =COUNTIF(B11:B10010,"<-20%")/COUNT(B11:B10010) -> 0.0182 | N20: 25% to 30% | O20: =COUNTIFS($B$11:$B$10010,">=25%",$B$11:$B$10010,"<30%") -> 585 | P20: =O20/$O$26 -> 0.0585
A21: 11 | B21: 0.18228106 | C21: =$B$4*(1+B21) -> 1.1822811e+08 | K21: Probability of Loss >30% | L21: =COUNTIF(B11:B10010,"<-30%")/COUNT(B11:B10010) -> 0.0026 | N21: 30% to 35% | O21: =COUNTIFS($B$11:$B$10010,">=30%",$B$11:$B$10010,"<35%") -> 328 | P21: =O21/$O$26 -> 0.0328
A22: 12 | B22: -0.10398468 | C22: =$B$4*(1+B22) -> 89601532 | N22: 35% to 40% | O22: =COUNTIFS($B$11:$B$10010,">=35%",$B$11:$B$10010,"<40%") -> 154 | P22: =O22/$O$26 -> 0.0154
A23: 13 | B23: 0.029963762 | C23: =$B$4*(1+B23) -> 1.0299638e+08 | K23: Metric | L23: Value / % | N23: 40% to 45% | O23: =COUNTIFS($B$11:$B$10010,">=40%",$B$11:$B$10010,"<45%") -> 58 | P23: =O23/$O$26 -> 0.0058
A24: 14 | B24: 0.32489143 | C24: =$B$4*(1+B24) -> 1.3248914e+08 | K24: Expected Portfolio Value | L24: =$B$4*(1+AVERAGE(B11:B10010)) -> 1.086473e+08 | N24: 45% to 50% | O24: =COUNTIFS($B$11:$B$10010,">=45%",$B$11:$B$10010,"<50%") -> 24 | P24: =O24/$O$26 -> 0.0024
A25: 15 | B25: 0.2837996 | C25: =$B$4*(1+B25) -> 1.2837996e+08 | K25: Worst Simulated Value | L25: =$B$4*(1+MIN(B11:B10010)) -> 54044086 | N25: Above 50% | O25: =COUNTIF($B$11:$B$10010,">=50%") -> 10 | P25: =O25/$O$26 -> 0.001
A26: 16 | B26: 0.22346204 | C26: =$B$4*(1+B26) -> 1.223462e+08 | K26: Best Simulated Value | L26: =$B$4*(1+MAX(B11:B10010)) -> 1.636758e+08 | N26: Total | O26: =SUM(O4:O25) -> 10000 | P26: =SUM(P4:P25) -> 1
A27: 17 | B27: -0.078626712 | C27: =$B$4*(1+B27) -> 92137329 | K27: 5% Worst Case Value | L27: =$B$4*(1+_xlfn.PERCENTILE.INC(B11:B10010,0.05)) -> 86006060
A28: 18 | B28: 0.053044387 | C28: =$B$4*(1+B28) -> 1.0530444e+08 | K28: 95% Best Case Value | L28: =$B$4*(1+_xlfn.PERCENTILE.INC(B11:B10010,0.95)) -> 1.3098071e+08
A29: 19 | B29: 0.1436005 | C29: =$B$4*(1+B29) -> 1.1436005e+08
A30: 20 | B30: -0.071058922 | C30: =$B$4*(1+B30) -> 92894108
A31: 21 | B31: 0.073018208 | C31: =$B$4*(1+B31) -> 1.0730182e+08
A32: 22 | B32: 0.28228612 | C32: =$B$4*(1+B32) -> 1.2822861e+08
A33: 23 | B33: 0.061589667 | C33: =$B$4*(1+B33) -> 1.0615897e+08
A34: 24 | B34: 0.23767628 | C34: =$B$4*(1+B34) -> 1.2376763e+08
A35: 25 | B35: 0.088967416 | C35: =$B$4*(1+B35) -> 1.0889674e+08
A36: 26 | B36: 0.059659093 | C36: =$B$4*(1+B36) -> 1.0596591e+08
A37: 27 | B37: -0.038938522 | C37: =$B$4*(1+B37) -> 96106148
A38: 28 | B38: 0.27091795 | C38: =$B$4*(1+B38) -> 1.2709179e+08
A39: 29 | B39: -0.29466718 | C39: =$B$4*(1+B39) -> 70533282
A40: 30 | B40: -0.02071706 | C40: =$B$4*(1+B40) -> 97928294
... A10010: 10000 | B10010: -0.12914674 | C10010: =$B$4*(1+B10010) -> 87085326

Sheet Risk Analysis and Hedging
A1: Portfolio Hedging Analysis | I1: MONTE CARLO VAR | L1: PARAMETRIC VAR
A3: Index futures values are assumed to be taken as on date of calculation, Values may differ later | I3: Confidence Level | J3: Return VaR | K3: ₹ VaR | L3: Confidence Level | M3: Return VAR | N3: ₹ VAR
I4: 0.95 | J4: =_xlfn.PERCENTILE.INC(Return,0.05) -> -0.1399394 | K4: =ABS('Monte Carlo Simulation'!$B$4*J4) -> 13993940 | L4: 0.95 | M4: ='Monte Carlo Simulation'!B5-(1.645*'Monte Carlo Simulation'!B6) -> -0.13690168 | N4: =ABS('Monte Carlo Simulation'!$B$4*M4) -> 13690168
I5: 0.99 | J5: =_xlfn.PERCENTILE.INC(Return,0.01) -> -0.2316935 | K5: =ABS('Monte Carlo Simulation'!B4*J5) -> 23169350 | L5: 0.99 | M5: ='Monte Carlo Simulation'!B5-(2.326*'Monte Carlo Simulation'!B6) -> -0.22909205 | N5: =ABS('Monte Carlo Simulation'!$B$4*M5) -> 22909205
B7: Contract Details | I7: Stress Test Scenarios
B8: Index | C8: Nifty | I8: Scenario | J8: Market Return | K8: Portfolio Return | L8: Portfolio Value | M8: Portfolio Loss (₹)
B9: Security Type | C9: Futures | I9: Mild Correction | J9: -0.1 | K9: =J9*'Portfolio Optimizer'!$C$21 -> -0.078124779 | L9: ='Monte Carlo Simulation'!$B$4*(1+'Risk Analysis and Hedging'!K9) -> 92187522 | M9: =L9-'Monte Carlo Simulation'!$B$4 -> -7812477.9
B10: Name of Security | C10: Nifty 28 Jul Fut | I10: Bear Market | J10: -0.2 | K10: =J10*'Portfolio Optimizer'!$C$21 -> -0.15624956 | L10: ='Monte Carlo Simulation'!$B$4*(1+'Risk Analysis and Hedging'!K10) -> 84375044 | M10: =L10-'Monte Carlo Simulation'!$B$4 -> -15624956
B11: CMP (Close on 17/7/26) | C11: 24345 | I11: Market Crash | J11: -0.3 | K11: =J11*'Portfolio Optimizer'!$C$21 -> -0.23437434 | L11: ='Monte Carlo Simulation'!$B$4*(1+'Risk Analysis and Hedging'!K11) -> 76562566 | M11: =L11-'Monte Carlo Simulation'!$B$4 -> -23437434
B12: Contract Size | C12: 65 | I12: Financial Crisis | J12: -0.4 | K12: =J12*'Portfolio Optimizer'!$C$21 -> -0.31249912 | L12: ='Monte Carlo Simulation'!$B$4*(1+'Risk Analysis and Hedging'!K12) -> 68750088 | M12: =L12-'Monte Carlo Simulation'!$B$4 -> -31249912
B13: Contract Value | C13: =C11*C12 -> 1582425 | I13: Black Swan | J13: -0.5 | K13: =J13*'Portfolio Optimizer'!$C$21 -> -0.39062389 | L13: ='Monte Carlo Simulation'!$B$4*(1+'Risk Analysis and Hedging'!K13) -> 60937611 | M13: =L13-'Monte Carlo Simulation'!$B$4 -> -39062389
B15: No of contracts for Hedging | I15: Hedge Values
B16: Scenario | C16: Hedge Ratios | I16: Scenario | J16: Hedge Ratios
C17: 1 | D17: 0.75 | E17: 0.5 | F17: 0.25 | J17: 1 | K17: 0.75 | L17: 0.5 | M17: 0.25
B18: =I18 -> Mild Correction | C18: =('Monte Carlo Simulation'!B4*'Risk Analysis and Hedging'!C17)/'Risk Analysis and Hedging'!C13 -> 63.194148 | D18: =('Monte Carlo Simulation'!$B$4*'Risk Analysis and Hedging'!D$17)/$C$13 -> 47.395611 | E18: =('Monte Carlo Simulation'!$B$4*'Risk Analysis and Hedging'!E$17)/$C$13 -> 31.597074 | F18: =('Monte Carlo Simulation'!$B$4*'Risk Analysis and Hedging'!F$17)/$C$13 -> 15.798537 | I18: =I9 -> Mild Correction | J18: =ABS($M9)*J$17 -> 7812477.9 | K18: =ABS($M9)*K$17 -> 5859358.4 | L18: =ABS($M9)*L$17 -> 3906238.9 | M18: =ABS($M9)*M$17 -> 1953119.5
B19: =I19 -> Bear Market | C19: =('Monte Carlo Simulation'!$B$4*$C$17)/$C$13 -> 63.194148 | D19: =('Monte Carlo Simulation'!$B$4*'Risk Analysis and Hedging'!D$17)/$C$13 -> 47.395611 | E19: =('Monte Carlo Simulation'!$B$4*'Risk Analysis and Hedging'!E$17)/$C$13 -> 31.597074 | F19: =('Monte Carlo Simulation'!$B$4*'Risk Analysis and Hedging'!F$17)/$C$13 -> 15.798537 | I19: =I10 -> Bear Market | J19: =ABS($M10)*J$17 -> 15624956 | K19: =ABS($M10)*K$17 -> 11718717 | L19: =ABS($M10)*L$17 -> 7812477.9 | M19: =ABS($M10)*M$17 -> 3906238.9
B20: =I20 -> Market Crash | C20: =('Monte Carlo Simulation'!$B$4*$C$17)/$C$13 -> 63.194148 | D20: =('Monte Carlo Simulation'!$B$4*'Risk Analysis and Hedging'!D$17)/$C$13 -> 47.395611 | E20: =('Monte Carlo Simulation'!$B$4*'Risk Analysis and Hedging'!E$17)/$C$13 -> 31.597074 | F20: =('Monte Carlo Simulation'!$B$4*'Risk Analysis and Hedging'!F$17)/$C$13 -> 15.798537 | I20: =I11 -> Market Crash | J20: =ABS($M11)*J$17 -> 23437434 | K20: =ABS($M11)*K$17 -> 17578075 | L20: =ABS($M11)*L$17 -> 11718717 | M20: =ABS($M11)*M$17 -> 5859358.4
B21: =I21 -> Financial Crisis | C21: =('Monte Carlo Simulation'!$B$4*$C$17)/$C$13 -> 63.194148 | D21: =('Monte Carlo Simulation'!$B$4*'Risk Analysis and Hedging'!D$17)/$C$13 -> 47.395611 | E21: =('Monte Carlo Simulation'!$B$4*'Risk Analysis and Hedging'!E$17)/$C$13 -> 31.597074 | F21: =('Monte Carlo Simulation'!$B$4*'Risk Analysis and Hedging'!F$17)/$C$13 -> 15.798537 | I21: =I12 -> Financial Crisis | J21: =ABS($M12)*J$17 -> 31249912 | K21: =ABS($M12)*K$17 -> 23437434 | L21: =ABS($M12)*L$17 -> 15624956 | M21: =ABS($M12)*M$17 -> 7812477.9
B22: =I22 -> Black Swan | C22: =('Monte Carlo Simulation'!$B$4*$C$17)/$C$13 -> 63.194148 | D22: =('Monte Carlo Simulation'!$B$4*'Risk Analysis and Hedging'!D$17)/$C$13 -> 47.395611 | E22: =('Monte Carlo Simulation'!$B$4*'Risk Analysis and Hedging'!E$17)/$C$13 -> 31.597074 | F22: =('Monte Carlo Simulation'!$B$4*'Risk Analysis and Hedging'!F$17)/$C$13 -> 15.798537 | I22: =I13 -> Black Swan | J22: =ABS($M13)*J$17 -> 39062389 | K22: =ABS($M13)*K$17 -> 29296792 | L22: =ABS($M13)*L$17 -> 19531195 | M22: =ABS($M13)*M$17 -> 9765597.4
B25: Alternatively, put option can also be considered for low cost hedging

Sheet MCS(Daily)
A1: Input | B1: Value
A2: Initial Investment | B2: 100000
A3: Expected Return | B3: =(1+'Monte Carlo Simulation'!B5)^(1/252)-1 -> 0.00032667233
A4: Portfolio Std Dev | B4: ='Portfolio Optimizer'!C16/SQRT(252) -> 0.0085278224
A5: Simulations | B5: 10000
A6: Days | B6: 252
A8: Iternations | B8: Value
A9: 1 | B9: =_xlfn.NORM.INV(RAND(),$B$3,$B$4) -> 0.0090083956
A10: 2 | B10: =_xlfn.NORM.INV(RAND(),$B$3,$B$4) -> -0.0081103269
A11: 3 | B11: =_xlfn.NORM.INV(RAND(),$B$3,$B$4) -> -0.014605429
A12: 4 | B12: =_xlfn.NORM.INV(RAND(),$B$3,$B$4) -> 0.0070769992
A13: 5 | B13: =_xlfn.NORM.INV(RAND(),$B$3,$B$4) -> 0.0021733182
A14: 6 | B14: =_xlfn.NORM.INV(RAND(),$B$3,$B$4) -> -0.0089650385
A15: 7 | B15: =_xlfn.NORM.INV(RAND(),$B$3,$B$4) -> -0.0031826479
A16: 8 | B16: =_xlfn.NORM.INV(RAND(),$B$3,$B$4) -> -0.02144353
A17: 9 | B17: =_xlfn.NORM.INV(RAND(),$B$3,$B$4) -> 0.0097559761
A18: 10 | B18: =_xlfn.NORM.INV(RAND(),$B$3,$B$4) -> 0.0024557422
A19: 11 | B19: =_xlfn.NORM.INV(RAND(),$B$3,$B$4) -> 0.0082435965
A20: 12 | B20: =_xlfn.NORM.INV(RAND(),$B$3,$B$4) -> 0.0041349226
... A10008: 10000 | B10008: =_xlfn.NORM.INV(RAND(),$B$3,$B$4) -> 0.007223107

Sheet Maruti
A1: Date | B1: Price | C1: Open | D1: High | E1: Low | F1: Vol. | G1: Change %
A2: 07/16/2026 | B2: 13783 | C2: 13605 | D2: 13845 | E2: 13584 | F2: 356.85K | G2: 0.0147
A3: 07/15/2026 | B3: 13583 | C3: 13503 | D3: 13606 | E3: 13435 | F3: 456.37K | G3: 0.007
A4: 07/14/2026 | B4: 13489 | C4: 13619 | D4: 13690 | E4: 13470 | F4: 368.65K | G4: -0.015
A5: 07/13/2026 | B5: 13695 | C5: 13682 | D5: 13841 | E5: 13536 | F5: 458.63K | G5: -0.0115
A6: 46302 | B6: 13854 | C6: 13800 | D6: 13987 | E6: 13776 | F6: 430.15K | G6: 0.0092
A7: 46272 | B7: 13728 | C7: 14000 | D7: 14037 | E7: 13700 | F7: 576.45K | G7: -0.016
A8: 46241 | B8: 13951 | C8: 14475 | D8: 14500 | E8: 13880 | F8: 481.08K | G8: -0.0404
A9: 46210 | B9: 14538 | C9: 14463 | D9: 14598 | E9: 14414 | F9: 524.76K | G9: 0.0057
A10: 46180 | B10: 14456 | C10: 14348 | D10: 14526 | E10: 14291 | F10: 214.69K | G10: 0.0063
A11: 46088 | B11: 14366 | C11: 14450 | D11: 14520 | E11: 14333 | F11: 384.19K | G11: 0.0013
A12: 46060 | B12: 14348 | C12: 14431 | D12: 14490 | E12: 14275 | F12: 327.09K | G12: -0.0033
A13: 46029 | B13: 14395 | C13: 14151 | D13: 14549 | E13: 14070 | F13: 1.40M | G13: 0.0198
A14: 06/30/2026 | B14: 14115 | C14: 13744 | D14: 14201 | E14: 13510 | F14: 1.51M | G14: 0.0524
A15: 06/29/2026 | B15: 13412 | C15: 13740 | D15: 13840 | E15: 13371 | F15: 1.36M | G15: -0.0242
A16: 06/25/2026 | B16: 13745 | C16: 13358 | D16: 13917 | E16: 13326 | F16: 981.56K | G16: 0.0375
A17: 06/24/2026 | B17: 13248 | C17: 13440 | D17: 13440 | E17: 13201 | F17: 327.50K | G17: -0.0151
A18: 06/23/2026 | B18: 13451 | C18: 13420 | D18: 13549 | E18: 13236 | F18: 398.56K | G18: 0.0022
A19: 06/22/2026 | B19: 13421 | C19: 13450 | D19: 13495 | E19: 13380 | F19: 254.53K | G19: 0.0019
A20: 06/19/2026 | B20: 13395 | C20: 13484 | D20: 13507 | E20: 13353 | F20: 719.76K | G20: -0.0066
A21: 06/18/2026 | B21: 13484 | C21: 13646 | D21: 13714 | E21: 13433 | F21: 373.51K | G21: -0.0107
A22: 06/17/2026 | B22: 13630 | C22: 13700 | D22: 13740 | E22: 13560 | F22: 241.53K | G22: -0.0045
A23: 06/16/2026 | B23: 13691 | C23: 13861 | D23: 13874 | E23: 13661 | F23: 280.51K | G23: -0.0083
A24: 06/15/2026 | B24: 13805 | C24: 13550 | D24: 13961 | E24: 13520 | F24: 613.28K | G24: 0.0328
A25: 46362 | B25: 13366 | C25: 13232 | D25: 13418 | E25: 13130 | F25: 559.04K | G25: 0.0205
A26: 46332 | B26: 13098 | C26: 13070 | D26: 13217 | E26: 12968 | F26: 308.71K | G26: 0.0019
A27: 46301 | B27: 13073 | C27: 13118 | D27: 13205 | E27: 13050 | F27: 203.89K | G27: -0.0036
A28: 46271 | B28: 13120 | C28: 13079 | D28: 13157 | E28: 12851 | F28: 428.32K | G28: 0.0161
A29: 46240 | B29: 12912 | C29: 12900 | D29: 13029 | E29: 12841 | F29: 372.90K | G29: -0.0106
A30: 46148 | B30: 13050 | C30: 13151 | D30: 13175 | E30: 12915 | F30: 295.70K | G30: -0.0011
A31: 46118 | B31: 13064 | C31: 12990 | D31: 13264 | E31: 12949 | F31: 465.07K | G31: 0.0015
A32: 46087 | B32: 13044 | C32: 13014 | D32: 13206 | E32: 12911 | F32: 607.81K | G32: 0.0017
A33: 46059 | B33: 13022 | C33: 12700 | D33: 13051 | E33: 12700 | F33: 586.60K | G33: 0.0059
A34: 46028 | B34: 12946 | C34: 13200 | D34: 13267 | E34: 12913 | F34: 295.36K | G34: -0.0138
A35: 05/29/2026 | B35: 13127 | C35: 13456 | D35: 13508 | E35: 13050 | F35: 963.29K | G35: -0.0177
A36: 05/27/2026 | B36: 13364 | C36: 13208 | D36: 13417 | E36: 13102 | F36: 322.02K | G36: 0.0118
A37: 05/26/2026 | B37: 13208 | C37: 13188 | D37: 13329 | E37: 13134 | F37: 256.90K | G37: 0.0029
A38: 05/25/2026 | B38: 13170 | C38: 13145 | D38: 13236 | E38: 13101 | F38: 276.55K | G38: 0.0141
A39: 05/22/2026 | B39: 12987 | C39: 13100 | D39: 13152 | E39: 12974 | F39: 387.98K | G39: -0.0018
A40: 05/21/2026 | B40: 13010 | C40: 13103 | D40: 13150 | E40: 12933 | F40: 213.10K | G40: 0.0005
A41: 05/20/2026 | B41: 13003 | C41: 12850 | D41: 13072 | E41: 12753 | F41: 300.70K | G41: 0.0036
A42: 05/19/2026 | B42: 12956 | C42: 13034 | D42: 13104 | E42: 12900 | F42: 342.74K | G42: -0.0046
A43: 05/18/2026 | B43: 13016 | C43: 13127 | D43: 13139 | E43: 12850 | F43: 373.18K | G43: -0.0155
A44: 05/15/2026 | B44: 13221 | C44: 13079 | D44: 13325 | E44: 13079 | F44: 268.21K | G44: 0.0112
A45: 05/14/2026 | B45: 13075 | C45: 13234 | D45: 13234 | E45: 12926 | F45: 286.65K | G45: -0.0021
A46: 05/13/2026 | B46: 13103 | C46: 13187 | D46: 13285 | E46: 12986 | F46: 307.03K | G46: -0.0052
A47: 46361 | B47: 13172 | C47: 13442 | D47: 13455 | E47: 13150 | F47: 302.51K | G47: -0.0231
A48: 46331 | B48: 13483 | C48: 13547 | D48: 13657 | E48: 13231 | F48: 634.35K | G48: -0.0177
A49: 46239 | B49: 13726 | C49: 13672 | D49: 13789 | E49: 13626 | F49: 270.51K | G49: -0.0032
A50: 46208 | B50: 13770 | C50: 13722 | D50: 13870 | E50: 13672 | F50: 726.20K | G50: 0.0035
A51: 46178 | B51: 13722 | C51: 13555 | D51: 13762 | E51: 13379 | F51: 435.21K | G51: 0.022
A52: 46147 | B52: 13426 | C52: 13560 | D52: 13568 | E52: 13360 | F52: 419.49K | G52: -0.0113
A53: 46117 | B53: 13580 | C53: 13559 | D53: 13976 | E53: 13435 | F53: 722.13K | G53: 0.02
A54: 04/30/2026 | B54: 13314 | C54: 13134 | D54: 13360 | E54: 12970 | F54: 612.98K | G54: 0.0043
A55: 04/29/2026 | B55: 13257 | C55: 13090 | D55: 13548 | E55: 13090 | F55: 754.80K | G55: 0.0283
A56: 04/28/2026 | B56: 12892 | C56: 13222 | D56: 13307 | E56: 12828 | F56: 836.68K | G56: -0.025
A57: 04/27/2026 | B57: 13222 | C57: 13153 | D57: 13270 | E57: 13043 | F57: 312.79K | G57: 0.0133
A58: 04/24/2026 | B58: 13048 | C58: 13200 | D58: 13253 | E58: 12978 | F58: 464.10K | G58: -0.0085
A59: 04/23/2026 | B59: 13160 | C59: 13250 | D59: 13358 | E59: 13125 | F59: 541.09K | G59: -0.0133
A60: 04/22/2026 | B60: 13337 | C60: 13452 | D60: 13530 | E60: 13300 | F60: 434.64K | G60: -0.0092
A61: 04/21/2026 | B61: 13461 | C61: 13456 | D61: 13543 | E61: 13421 | F61: 292.88K | G61: 0.0008
A62: 04/20/2026 | B62: 13450 | C62: 13474 | D62: 13533 | E62: 13329 | F62: 348.63K | G62: -0.0002
A63: 04/17/2026 | B63: 13453 | C63: 13300 | D63: 13647 | E63: 13256 | F63: 549.31K | G63: 0.0088
A64: 04/16/2026 | B64: 13335 | C64: 13380 | D64: 13435 | E64: 13237 | F64: 527.31K | G64: 0.0035
A65: 04/15/2026 | B65: 13289 | C65: 13250 | D65: 13473 | E65: 13200 | F65: 699.46K | G65: 0.0163
A66: 04/13/2026 | B66: 13076 | C66: 13402 | D66: 13420 | E66: 12966 | F66: 1.35M | G66: -0.0462
A67: 46299 | B67: 13709 | C67: 13650 | D67: 13797 | E67: 13590 | F67: 471.92K | G67: 0.0088
A68: 46269 | B68: 13589 | C68: 13570 | D68: 13773 | E68: 13330 | F68: 549.91K | G68: -0.001
A69: 46238 | B69: 13602 | C69: 13350 | D69: 13745 | E69: 13210 | F69: 1.03M | G69: 0.0628
A70: 46207 | B70: 12798 | C70: 12640 | D70: 12835 | E70: 12496 | F70: 359.54K | G70: 0.0087
A71: 46177 | B71: 12688 | C71: 12631 | D71: 12720 | E71: 12420 | F71: 382.65K | G71: 0.0045
A72: 46057 | B72: 12631 | C72: 12389 | D72: 12673 | E72: 12239 | F72: 438.23K | G72: 0.0098
A73: 46026 | B73: 12509 | C73: 12900 | D73: 12900 | E73: 12333 | F73: 501.88K | G73: 0.0165
A74: 03/30/2026 | B74: 12306 | C74: 12300 | D74: 12424 | E74: 12201 | F74: 635.68K | G74: -0.0067
A75: 03/27/2026 | B75: 12389 | C75: 12626 | D75: 12646 | E75: 12342 | F75: 775.34K | G75: -0.0253
A76: 03/25/2026 | B76: 12711 | C76: 12549 | D76: 12780 | E76: 12506 | F76: 540.65K | G76: 0.0198
A77: 03/24/2026 | B77: 12464 | C77: 12600 | D77: 12650 | E77: 12332 | F77: 583.57K | G77: 0.0088
A78: 03/23/2026 | B78: 12355 | C78: 12501 | D78: 12501 | E78: 12278 | F78: 517.99K | G78: -0.0195
A79: 03/20/2026 | B79: 12601 | C79: 12605 | D79: 12756 | E79: 12556 | F79: 725.48K | G79: 0.0002
A80: 03/19/2026 | B80: 12599 | C80: 12768 | D80: 12838 | E80: 12505 | F80: 569.35K | G80: -0.0344
A81: 03/18/2026 | B81: 13048 | C81: 13100 | D81: 13176 | E81: 13015 | F81: 458.83K | G81: 0.0059
A82: 03/17/2026 | B82: 12972 | C82: 12790 | D82: 13100 | E82: 12686 | F82: 1.18M | G82: 0.0169
A83: 03/16/2026 | B83: 12757 | C83: 12532 | D83: 12874 | E83: 12400 | F83: 1.42M | G83: 0.0132
A84: 03/13/2026 | B84: 12591 | C84: 12899 | D84: 12962 | E84: 12483 | F84: 939.59K | G84: -0.0323
A85: 46359 | B85: 13011 | C85: 13430 | D85: 13430 | E85: 12966 | F85: 544.68K | G85: -0.036
A86: 46329 | B86: 13497 | C86: 13850 | D86: 13948 | E86: 13441 | F86: 392.18K | G86: -0.0267
A87: 46298 | B87: 13867 | C87: 13721 | D87: 13909 | E87: 13505 | F87: 353.72K | G87: 0.0266
A88: 46268 | B88: 13508 | C88: 13800 | D88: 13800 | E88: 13365 | F88: 676.22K | G88: -0.046
A89: 46176 | B89: 14159 | C89: 14339 | D89: 14466 | E89: 14115 | F89: 390.63K | G89: -0.0178
A90: 46145 | B90: 14415 | C90: 14300 | D90: 14570 | E90: 14081 | F90: 448.65K | G90: 0.0182
A91: 46115 | B91: 14158 | C91: 14150 | D91: 14184 | E91: 13794 | F91: 710.37K | G91: -0.016
A92: 46056 | B92: 14388 | C92: 14407 | D92: 14684 | E92: 14204 | F92: 603.74K | G92: -0.0316
A93: 02/27/2026 | B93: 14857 | C93: 15110 | D93: 15192 | E93: 14804 | F93: 478.16K | G93: -0.0234
A94: 02/26/2026 | B94: 15213 | C94: 15145 | D94: 15224 | E94: 15046 | F94: 308.21K | G94: 0.0095
A95: 02/25/2026 | B95: 15070 | C95: 14860 | D95: 15133 | E95: 14837 | F95: 356.50K | G95: 0.0096
A96: 02/24/2026 | B96: 14926 | C96: 15001 | D96: 15062 | E96: 14904 | F96: 300.99K | G96: -0.0097
A97: 02/23/2026 | B97: 15072 | C97: 15050 | D97: 15118 | E97: 14984 | F97: 242.97K | G97: 0.0063
A98: 02/20/2026 | B98: 14977 | C98: 14903 | D98: 15077 | E98: 14848 | F98: 515.85K | G98: 0.005
A99: 02/19/2026 | B99: 14903 | C99: 15163 | D99: 15279 | E99: 14853 | F99: 152.79K | G99: -0.0172
A100: 02/18/2026 | B100: 15164 | C100: 15208 | D100: 15239 | E100: 15074 | F100: 280.77K | G100: -0.001
...

Sheet Sun Pharma
A1: Date | B1: Price | C1: Open | D1: High | E1: Low | F1: Vol. | G1: Change %
A2: 07/16/2026 | B2: 1950.1 | C2: 1950 | D2: 1957.7 | E2: 1943 | F2: 1.40M | G2: -0.0007
A3: 07/15/2026 | B3: 1951.5 | C3: 1955 | D3: 1962.7 | E3: 1943.3 | F3: 2.28M | G3: 0.0046
A4: 07/14/2026 | B4: 1942.6 | C4: 1910 | D4: 1950.8 | E4: 1910 | F4: 2.82M | G4: 0.011
A5: 07/13/2026 | B5: 1921.4 | C5: 1925.9 | D5: 1933.1 | E5: 1911 | F5: 1.57M | G5: -0.0073
A6: 46302 | B6: 1935.5 | C6: 1942.8 | D6: 1953.9 | E6: 1926.6 | F6: 1.48M | G6: -0.0017
A7: 46272 | B7: 1938.7 | C7: 1889.9 | D7: 1952 | E7: 1888.2 | F7: 4.45M | G7: 0.0267
A8: 46241 | B8: 1888.2 | C8: 1904 | D8: 1929.5 | E8: 1875.1 | F8: 2.79M | G8: -0.008
A9: 46210 | B9: 1903.4 | C9: 1900.6 | D9: 1924.9 | E9: 1898.6 | F9: 2.06M | G9: -0.0049
A10: 46180 | B10: 1912.8 | C10: 1904 | D10: 1917 | E10: 1900 | F10: 1.21M | G10: 0.0042
A11: 46088 | B11: 1904.8 | C11: 1880 | D11: 1925.1 | E11: 1871.6 | F11: 2.17M | G11: 0.0181
A12: 46060 | B12: 1871 | C12: 1876 | D12: 1882 | E12: 1868.3 | F12: 1.49M | G12: 0.0026
A13: 46029 | B13: 1866.2 | C13: 1877.9 | D13: 1887.4 | E13: 1860.2 | F13: 1.23M | G13: 0.002
A14: 06/30/2026 | B14: 1862.5 | C14: 1885 | D14: 1892.9 | E14: 1859.4 | F14: 2.35M | G14: -0.0066
A15: 06/29/2026 | B15: 1874.8 | C15: 1876.8 | D15: 1897.1 | E15: 1855.9 | F15: 1.66M | G15: 0.0064
A16: 06/25/2026 | B16: 1862.8 | C16: 1870 | D16: 1887 | E16: 1858 | F16: 1.82M | G16: -0.0062
A17: 06/24/2026 | B17: 1874.4 | C17: 1868 | D17: 1882.1 | E17: 1864.9 | F17: 1.41M | G17: 0.0034
A18: 06/23/2026 | B18: 1868 | C18: 1870 | D18: 1902.4 | E18: 1861.2 | F18: 2.81M | G18: 0.0027
A19: 06/22/2026 | B19: 1862.9 | C19: 1845 | D19: 1865.2 | E19: 1834 | F19: 1.59M | G19: 0.0134
A20: 06/19/2026 | B20: 1838.3 | C20: 1824 | D20: 1842.7 | E20: 1820.9 | F20: 2.13M | G20: 0.0074
A21: 06/18/2026 | B21: 1824.8 | C21: 1817.5 | D21: 1830 | E21: 1812.5 | F21: 2.05M | G21: 0.0024
A22: 06/17/2026 | B22: 1820.4 | C22: 1814 | D22: 1823.4 | E22: 1802.6 | F22: 1.77M | G22: 0.0109
A23: 06/16/2026 | B23: 1800.7 | C23: 1808 | D23: 1809.9 | E23: 1792.6 | F23: 1.37M | G23: -0.0029
A24: 06/15/2026 | B24: 1806 | C24: 1818 | D24: 1818 | E24: 1797.8 | F24: 2.19M | G24: -0.0009
A25: 46362 | B25: 1807.7 | C25: 1807 | D25: 1814.5 | E25: 1792.5 | F25: 1.24M | G25: 0.0075
A26: 46332 | B26: 1794.2 | C26: 1780 | D26: 1805 | E26: 1778.7 | F26: 1.86M | G26: 0.0044
A27: 46301 | B27: 1786.4 | C27: 1779.6 | D27: 1797.6 | E27: 1771 | F27: 1.88M | G27: 0.0042
A28: 46271 | B28: 1779 | C28: 1787.7 | D28: 1796.6 | E28: 1766.1 | F28: 3.76M | G28: -0.0055
A29: 46240 | B29: 1788.8 | C29: 1780.7 | D29: 1803.5 | E29: 1773.5 | F29: 3.10M | G29: 0.0037
A30: 46148 | B30: 1782.2 | C30: 1789 | D30: 1802.9 | E30: 1779 | F30: 2.50M | G30: 0.0012
A31: 46118 | B31: 1780.1 | C31: 1787 | D31: 1793.4 | E31: 1768.6 | F31: 2.34M | G31: -0.0047
A32: 46087 | B32: 1788.5 | C32: 1781 | D32: 1796.3 | E32: 1756.8 | F32: 4.21M | G32: -0.0008
A33: 46059 | B33: 1789.9 | C33: 1794.2 | D33: 1800 | E33: 1766.5 | F33: 2.89M | G33: -0.0037
A34: 46028 | B34: 1796.5 | C34: 1812 | D34: 1812.1 | E34: 1777.1 | F34: 2.05M | G34: -0.0015
A35: 05/29/2026 | B35: 1799.2 | C35: 1844.3 | D35: 1852.8 | E35: 1785.3 | F35: 10.06M | G35: -0.0245
A36: 05/27/2026 | B36: 1844.3 | C36: 1865 | D36: 1882 | E36: 1830 | F36: 1.39M | G36: 0.0019
A37: 05/26/2026 | B37: 1840.8 | C37: 1830 | D37: 1844.9 | E37: 1815.9 | F37: 2.34M | G37: 0.0001
A38: 05/25/2026 | B38: 1840.6 | C38: 1840 | D38: 1849 | E38: 1825 | F38: 3.05M | G38: -0.0022
A39: 05/22/2026 | B39: 1844.6 | C39: 1903 | D39: 1903 | E39: 1833.1 | F39: 3.61M | G39: -0.0247
A40: 05/21/2026 | B40: 1891.3 | C40: 1892 | D40: 1899.6 | E40: 1868.1 | F40: 1.61M | G40: 0.0059
A41: 05/20/2026 | B41: 1880.3 | C41: 1880 | D41: 1892.9 | E41: 1872 | F41: 1.38M | G41: -0.0011
A42: 05/19/2026 | B42: 1882.3 | C42: 1900.5 | D42: 1916.6 | E42: 1880 | F42: 2.20M | G42: -0.0123
A43: 05/18/2026 | B43: 1905.8 | C43: 1878.2 | D43: 1911 | E43: 1865 | F43: 3.46M | G43: 0.0147
A44: 05/15/2026 | B44: 1878.2 | C44: 1874 | D44: 1887.9 | E44: 1863.2 | F44: 2.76M | G44: 0.0081
A45: 05/14/2026 | B45: 1863.2 | C45: 1852 | D45: 1867.5 | E45: 1829.7 | F45: 2.43M | G45: 0.021
A46: 05/13/2026 | B46: 1824.8 | C46: 1845.7 | D46: 1860 | E46: 1820 | F46: 1.97M | G46: -0.0113
A47: 46361 | B47: 1845.7 | C47: 1875 | D47: 1879.4 | E47: 1840 | F47: 3.26M | G47: -0.0144
A48: 46331 | B48: 1872.7 | C48: 1827.2 | D48: 1885.8 | E48: 1825 | F48: 2.56M | G48: 0.0134
A49: 46239 | B49: 1847.9 | C49: 1822 | D49: 1857.5 | E49: 1819.2 | F49: 2.84M | G49: 0.0074
A50: 46208 | B50: 1834.4 | C50: 1850.2 | D50: 1857.1 | E50: 1826.3 | F50: 2.20M | G50: -0.0085
A51: 46178 | B51: 1850.2 | C51: 1837 | D51: 1857.8 | E51: 1818.4 | F51: 3.25M | G51: 0.0161
A52: 46147 | B52: 1820.8 | C52: 1828.5 | D52: 1831.7 | E52: 1798.6 | F52: 3.01M | G52: -0.0015
A53: 46117 | B53: 1823.5 | C53: 1820 | D53: 1841 | E53: 1810 | F53: 4.21M | G53: 0.0084
A54: 04/30/2026 | B54: 1808.3 | C54: 1771 | D54: 1815 | E54: 1761.4 | F54: 4.75M | G54: 0.0166
A55: 04/29/2026 | B55: 1778.7 | C55: 1756 | D55: 1789.8 | E55: 1750 | F55: 9.81M | G55: 0.018
A56: 04/28/2026 | B56: 1747.3 | C56: 1724 | D56: 1763.9 | E56: 1714.3 | F56: 16.60M | G56: 0.008
A57: 04/27/2026 | B57: 1733.5 | C57: 1625 | D57: 1766.9 | E57: 1621.9 | F57: 27.00M | G57: 0.0698
A58: 04/24/2026 | B58: 1620.4 | C58: 1670.4 | D58: 1673.3 | E58: 1613.6 | F58: 9.61M | G58: -0.0355
A59: 04/23/2026 | B59: 1680.1 | C59: 1669 | D59: 1713 | E59: 1661.2 | F59: 3.25M | G59: 0.0062
A60: 04/22/2026 | B60: 1669.8 | C60: 1665.2 | D60: 1673.9 | E60: 1652.4 | F60: 2.17M | G60: 0.0028
A61: 04/21/2026 | B61: 1665.2 | C61: 1667.2 | D61: 1682.9 | E61: 1659.9 | F61: 3.63M | G61: -0.002
A62: 04/20/2026 | B62: 1668.6 | C62: 1680 | D62: 1680 | E62: 1665 | F62: 1.83M | G62: -0.0041
A63: 04/17/2026 | B63: 1675.5 | C63: 1696.9 | D63: 1696.9 | E63: 1670.5 | F63: 3.15M | G63: -0.0104
A64: 04/16/2026 | B64: 1693.1 | C64: 1713.9 | D64: 1713.9 | E64: 1666.6 | F64: 4.51M | G64: -0.0021
A65: 04/15/2026 | B65: 1696.6 | C65: 1675 | D65: 1699.2 | E65: 1657.7 | F65: 3.76M | G65: 0.0269
A66: 04/13/2026 | B66: 1652.2 | C66: 1654.9 | D66: 1668.7 | E66: 1640.1 | F66: 3.75M | G66: -0.0016
A67: 46299 | B67: 1654.9 | C67: 1699.2 | D67: 1700 | E67: 1630.4 | F67: 8.09M | G67: -0.0362
A68: 46269 | B68: 1717.1 | C68: 1702.7 | D68: 1730.9 | E68: 1702.7 | F68: 3.28M | G68: 0.0015
A69: 46238 | B69: 1714.6 | C69: 1730 | D69: 1749.2 | E69: 1685.5 | F69: 4.86M | G69: -0.002
A70: 46207 | B70: 1718 | C70: 1689.8 | D70: 1723.9 | E70: 1681.3 | F70: 2.47M | G70: 0.0138
A71: 46177 | B71: 1694.6 | C71: 1684.3 | D71: 1699 | E71: 1654.9 | F71: 3.53M | G71: 0.0006
A72: 46057 | B72: 1693.6 | C72: 1665 | D72: 1700 | E72: 1620 | F72: 3.94M | G72: -0.0202
A73: 46026 | B73: 1728.5 | C73: 1762.1 | D73: 1788 | E73: 1713.2 | F73: 3.25M | G73: -0.0163
A74: 03/30/2026 | B74: 1757.2 | C74: 1786.8 | D74: 1790 | E74: 1750.1 | F74: 4.18M | G74: -0.0203
A75: 03/27/2026 | B75: 1793.6 | C75: 1785 | D75: 1819 | E75: 1785 | F75: 2.98M | G75: -0.001
A76: 03/25/2026 | B76: 1795.4 | C76: 1766.7 | D76: 1809.5 | E76: 1755.5 | F76: 1.90M | G76: 0.024
A77: 03/24/2026 | B77: 1753.3 | C77: 1775 | D77: 1779.9 | E77: 1745.1 | F77: 2.04M | G77: -0.0029
A78: 03/23/2026 | B78: 1758.4 | C78: 1774.8 | D78: 1775 | E78: 1741.1 | F78: 2.78M | G78: -0.0105
A79: 03/20/2026 | B79: 1777.1 | C79: 1755.1 | D79: 1781.3 | E79: 1754.3 | F79: 3.59M | G79: 0.0187
A80: 03/19/2026 | B80: 1744.4 | C80: 1760.5 | D80: 1784 | E80: 1737.9 | F80: 2.30M | G80: -0.0191
A81: 03/18/2026 | B81: 1778.3 | C81: 1799.6 | D81: 1805 | E81: 1773.2 | F81: 2.44M | G81: -0.009
A82: 03/17/2026 | B82: 1794.4 | C82: 1794.1 | D82: 1806.1 | E82: 1781.1 | F82: 1.98M | G82: 0.0063
A83: 03/16/2026 | B83: 1783.2 | C83: 1801.6 | D83: 1818 | E83: 1768.8 | F83: 2.45M | G83: -0.0102
A84: 03/13/2026 | B84: 1801.6 | C84: 1822 | D84: 1833.3 | E84: 1797 | F84: 2.55M | G84: -0.013
A85: 46359 | B85: 1825.3 | C85: 1828 | D85: 1833.6 | E85: 1808.4 | F85: 2.61M | G85: -0.0003
A86: 46329 | B86: 1825.9 | C86: 1823 | D86: 1843 | E86: 1818.1 | F86: 2.51M | G86: 0.0072
A87: 46298 | B87: 1812.8 | C87: 1810 | D87: 1825.1 | E87: 1803.3 | F87: 3.30M | G87: 0.003
A88: 46268 | B88: 1807.4 | C88: 1772.9 | D88: 1815 | E88: 1770 | F88: 4.11M | G88: 0.0044
A89: 46176 | B89: 1799.4 | C89: 1784.5 | D89: 1805.6 | E89: 1771.8 | F89: 3.67M | G89: 0.0083
A90: 46145 | B90: 1784.5 | C90: 1750 | D90: 1794.9 | E90: 1748 | F90: 3.60M | G90: 0.0194
A91: 46115 | B91: 1750.5 | C91: 1721.2 | D91: 1757.2 | E91: 1721 | F91: 4.91M | G91: -0.0011
A92: 46056 | B92: 1752.5 | C92: 1712 | D92: 1759.9 | E92: 1712 | F92: 3.92M | G92: 0.0089
A93: 02/27/2026 | B93: 1737 | C93: 1779 | D93: 1788.1 | E93: 1730.9 | F93: 3.04M | G93: -0.0273
A94: 02/26/2026 | B94: 1785.7 | C94: 1764.2 | D94: 1792.2 | E94: 1760.3 | F94: 2.08M | G94: 0.0122
A95: 02/25/2026 | B95: 1764.2 | C95: 1742 | D95: 1770.4 | E95: 1733.4 | F95: 1.20M | G95: 0.0187
A96: 02/24/2026 | B96: 1731.8 | C96: 1732 | D96: 1745.9 | E96: 1723.7 | F96: 2.77M | G96: -0.0003
A97: 02/23/2026 | B97: 1732.3 | C97: 1732.9 | D97: 1735.8 | E97: 1720.2 | F97: 1.55M | G97: 0.0046
A98: 02/20/2026 | B98: 1724.4 | C98: 1710.1 | D98: 1727 | E98: 1708.1 | F98: 1.20M | G98: 0.0064
A99: 02/19/2026 | B99: 1713.4 | C99: 1722.2 | D99: 1727 | E99: 1710 | F99: 1.14M | G99: -0.0064
A100: 02/18/2026 | B100: 1724.4 | C100: 1720.4 | D100: 1730.6 | E100: 1717.1 | F100: 1.26M | G100: 0.0043
...

Sheet HUL
A1: Date | B1: Price | C1: Open | D1: High | E1: Low | F1: Vol. | G1: Change %
A2: 07/16/2026 | B2: 2098.4 | C2: 2104.9 | D2: 2123 | E2: 2096 | F2: 2.14M | G2: -0.002
A3: 07/15/2026 | B3: 2102.6 | C3: 2121 | D3: 2128.5 | E3: 2091 | F3: 2.03M | G3: -0.0083
A4: 07/14/2026 | B4: 2120.2 | C4: 2125 | D4: 2145 | E4: 2116.1 | F4: 2.68M | G4: -0.0049
A5: 07/13/2026 | B5: 2130.6 | C5: 2143 | D5: 2143 | E5: 2120 | F5: 1.83M | G5: -0.0093
A6: 46302 | B6: 2150.6 | C6: 2151.5 | D6: 2178 | E6: 2145 | F6: 1.67M | G6: 0.0028
A7: 46272 | B7: 2144.5 | C7: 2139 | D7: 2166.8 | E7: 2137.1 | F7: 2.20M | G7: 0.0041
A8: 46241 | B8: 2135.8 | C8: 2199 | D8: 2199 | E8: 2130 | F8: 1.33M | G8: -0.033
A9: 46210 | B9: 2208.8 | C9: 2200 | D9: 2219.4 | E9: 2193.7 | F9: 2.55M | G9: 0.0031
A10: 46180 | B10: 2202 | C10: 2202.1 | D10: 2221.4 | E10: 2190.3 | F10: 2.13M | G10: 0.0004
A11: 46088 | B11: 2201.2 | C11: 2224.9 | D11: 2239.3 | E11: 2190 | F11: 1.54M | G11: -0.0043
A12: 46060 | B12: 2210.6 | C12: 2186 | D12: 2216 | E12: 2179.2 | F12: 2.59M | G12: 0.0131
A13: 46029 | B13: 2182 | C13: 2133.5 | D13: 2190 | E13: 2120.2 | F13: 2.50M | G13: 0.0301
A14: 06/30/2026 | B14: 2118.2 | C14: 2151 | D14: 2151.3 | E14: 2114.2 | F14: 2.36M | G14: -0.0154
A15: 06/29/2026 | B15: 2151.3 | C15: 2172 | D15: 2189.9 | E15: 2143 | F15: 1.42M | G15: -0.0105
A16: 06/25/2026 | B16: 2174.2 | C16: 2161 | D16: 2200.9 | E16: 2161 | F16: 1.90M | G16: 0.0076
A17: 06/24/2026 | B17: 2157.8 | C17: 2160 | D17: 2166 | E17: 2140 | F17: 942.27K | G17: -0.0011
A18: 06/23/2026 | B18: 2160.1 | C18: 2160.1 | D18: 2179.7 | E18: 2156 | F18: 710.08K | G18: -0.0114
A19: 06/22/2026 | B19: 2184.9 | C19: 2203.7 | D19: 2208.2 | E19: 2182.5 | F19: 765.86K | G19: -0.0044
A20: 06/19/2026 | B20: 2194.6 | C20: 2209.6 | D20: 2210.6 | E20: 2179.9 | F20: 1.51M | G20: -0.0108
A21: 06/18/2026 | B21: 2218.5 | C21: 2208.7 | D21: 2221.6 | E21: 2196.8 | F21: 1.12M | G21: 0.0095
A22: 06/17/2026 | B22: 2197.6 | C22: 2201.1 | D22: 2224.6 | E22: 2183 | F22: 1.51M | G22: -0.001
A23: 06/16/2026 | B23: 2199.9 | C23: 2161 | D23: 2209 | E23: 2160.1 | F23: 1.34M | G23: 0.0203
A24: 06/15/2026 | B24: 2156.1 | C24: 2200 | D24: 2211 | E24: 2150 | F24: 1.44M | G24: -0.0059
A25: 46362 | B25: 2168.8 | C25: 2151.2 | D25: 2179.4 | E25: 2145 | F25: 1.16M | G25: 0.0136
A26: 46332 | B26: 2139.8 | C26: 2164 | D26: 2165 | E26: 2135.3 | F26: 1.18M | G26: -0.0137
A27: 46301 | B27: 2169.5 | C27: 2134.9 | D27: 2204.9 | E27: 2133.5 | F27: 2.33M | G27: 0.0172
A28: 46271 | B28: 2132.8 | C28: 2119.7 | D28: 2138.6 | E28: 2110.1 | F28: 1.46M | G28: 0.0108
A29: 46240 | B29: 2110.1 | C29: 2105.3 | D29: 2125 | E29: 2091.5 | F29: 1.60M | G29: -0.0054
A30: 46148 | B30: 2121.5 | C30: 2086.7 | D30: 2127.5 | E30: 2077.2 | F30: 1.82M | G30: 0.0202
A31: 46118 | B31: 2079.4 | C31: 2089 | D31: 2110.9 | E31: 2073.5 | F31: 2.14M | G31: -0.0054
A32: 46087 | B32: 2090.6 | C32: 2092 | D32: 2099.6 | E32: 2072.2 | F32: 1.54M | G32: -0.0015
A33: 46059 | B33: 2093.7 | C33: 2079 | D33: 2097 | E33: 2065.7 | F33: 2.15M | G33: 0.0045
A34: 46028 | B34: 2084.3 | C34: 2158.5 | D34: 2167.5 | E34: 2080.3 | F34: 1.47M | G34: -0.0321
A35: 05/29/2026 | B35: 2153.5 | C35: 2133.5 | D35: 2207.8 | E35: 2118.1 | F35: 17.70M | G35: -0.0204
A36: 05/27/2026 | B36: 2198.4 | C36: 2205.1 | D36: 2214.6 | E36: 2187 | F36: 616.54K | G36: -0.005
A37: 05/26/2026 | B37: 2209.4 | C37: 2199.6 | D37: 2220 | E37: 2190 | F37: 2.30M | G37: 0.0059
A38: 05/25/2026 | B38: 2196.5 | C38: 2215 | D38: 2238.1 | E38: 2192.9 | F38: 780.72K | G38: -0.0032
A39: 05/22/2026 | B39: 2203.6 | C39: 2180 | D39: 2224.5 | E39: 2175.4 | F39: 1.38M | G39: 0.0113
A40: 05/21/2026 | B40: 2179 | C40: 2224 | D40: 2229 | E40: 2176 | F40: 1.58M | G40: -0.0137
A41: 05/20/2026 | B41: 2209.3 | C41: 2224.9 | D41: 2226.9 | E41: 2201 | F41: 1.07M | G41: -0.0106
A42: 05/19/2026 | B42: 2232.9 | C42: 2242 | D42: 2282 | E42: 2229.5 | F42: 1.15M | G42: -0.0094
A43: 05/18/2026 | B43: 2254.2 | C43: 2263.1 | D43: 2265 | E43: 2224.7 | F43: 1.12M | G43: -0.0079
A44: 05/15/2026 | B44: 2272.2 | C44: 2248.7 | D44: 2298.9 | E44: 2246.2 | F44: 1.04M | G44: 0.0105
A45: 05/14/2026 | B45: 2248.7 | C45: 2268 | D45: 2285.9 | E45: 2245 | F45: 1.38M | G45: -0.0082
A46: 05/13/2026 | B46: 2267.3 | C46: 2265 | D46: 2295.8 | E46: 2250 | F46: 1.31M | G46: 0.0023
A47: 46361 | B47: 2262 | C47: 2285.3 | D47: 2307 | E47: 2256 | F47: 983.51K | G47: -0.0196
A48: 46331 | B48: 2307.2 | C48: 2277.1 | D48: 2317.1 | E48: 2259.2 | F48: 1.90M | G48: 0.0085
A49: 46239 | B49: 2287.7 | C49: 2272.2 | D49: 2297.3 | E49: 2256 | F49: 1.10M | G49: 0.0068
A50: 46208 | B50: 2272.2 | C50: 2310 | D50: 2327.9 | E50: 2268.1 | F50: 1.86M | G50: -0.0194
A51: 46178 | B51: 2317.1 | C51: 2330 | D51: 2339.4 | E51: 2288.3 | F51: 1.20M | G51: -0.0044
A52: 46147 | B52: 2327.4 | C52: 2301.5 | D52: 2335.4 | E52: 2288.1 | F52: 1.74M | G52: 0.0078
A53: 46117 | B53: 2309.3 | C53: 2268.8 | D53: 2365.8 | E53: 2268.8 | F53: 2.55M | G53: 0.0259
A54: 04/30/2026 | B54: 2250.9 | C54: 2312 | D54: 2368.8 | E54: 2211.6 | F54: 4.43M | G54: -0.0274
A55: 04/29/2026 | B55: 2314.4 | C55: 2305 | D55: 2349.7 | E55: 2291 | F55: 1.78M | G55: 0.0109
A56: 04/28/2026 | B56: 2289.5 | C56: 2321 | D56: 2334.4 | E56: 2281.1 | F56: 1.63M | G56: -0.0167
A57: 04/27/2026 | B57: 2328.3 | C57: 2334.9 | D57: 2362.8 | E57: 2325 | F57: 1.10M | G57: 0.0004
A58: 04/24/2026 | B58: 2327.3 | C58: 2388.6 | D58: 2388.6 | E58: 2299 | F58: 1.68M | G58: -0.0165
A59: 04/23/2026 | B59: 2366.4 | C59: 2336 | D59: 2400 | E59: 2336 | F59: 2.06M | G59: -0.001
A60: 04/22/2026 | B60: 2368.8 | C60: 2310.4 | D60: 2408 | E60: 2310.4 | F60: 5.56M | G60: 0.0251
A61: 04/21/2026 | B61: 2310.7 | C61: 2238.7 | D61: 2335.7 | E61: 2227.2 | F61: 3.22M | G61: 0.0355
A62: 04/20/2026 | B62: 2231.5 | C62: 2240.8 | D62: 2253.4 | E62: 2223.2 | F62: 1.46M | G62: -0.0042
A63: 04/17/2026 | B63: 2240.8 | C63: 2142 | D63: 2245 | E63: 2133 | F63: 4.88M | G63: 0.0475
A64: 04/16/2026 | B64: 2139.1 | C64: 2158 | D64: 2163.7 | E64: 2129.1 | F64: 1.85M | G64: -0.0086
A65: 04/15/2026 | B65: 2157.6 | C65: 2140.9 | D65: 2168 | E65: 2140.9 | F65: 1.55M | G65: 0.0143
A66: 04/13/2026 | B66: 2127.2 | C66: 2131 | D66: 2140.7 | E66: 2113.5 | F66: 1.99M | G66: -0.013
A67: 46299 | B67: 2155.3 | C67: 2133.2 | D67: 2170 | E67: 2121.4 | F67: 2.14M | G67: 0.0104
A68: 46269 | B68: 2133.2 | C68: 2145.5 | D68: 2162.9 | E68: 2115 | F68: 2.51M | G68: -0.0058
A69: 46238 | B69: 2145.6 | C69: 2130 | D69: 2192.8 | E69: 2130 | F69: 3.79M | G69: 0.0166
A70: 46207 | B70: 2110.6 | C70: 2064.7 | D70: 2119.5 | E70: 2050.8 | F70: 2.71M | G70: 0.0124
A71: 46177 | B71: 2084.8 | C71: 2065.3 | D71: 2092.8 | E71: 2041.9 | F71: 1.66M | G71: 0.0094
A72: 46057 | B72: 2065.3 | C72: 2055 | D72: 2069.9 | E72: 2022.5 | F72: 1.43M | G72: 0.0003
A73: 46026 | B73: 2064.7 | C73: 2119.9 | D73: 2119.9 | E73: 2052 | F73: 2.03M | G73: 0.0046
A74: 03/30/2026 | B74: 2055.2 | C74: 2064 | D74: 2082.4 | E74: 2046.2 | F74: 2.48M | G74: -0.0093
A75: 03/27/2026 | B75: 2074.4 | C75: 2123.3 | D75: 2127 | E75: 2069.5 | F75: 2.79M | G75: -0.0283
A76: 03/25/2026 | B76: 2134.8 | C76: 2098 | D76: 2154.7 | E76: 2086 | F76: 2.07M | G76: 0.0239
A77: 03/24/2026 | B77: 2085 | C77: 2070 | D77: 2115 | E77: 2066 | F77: 1.70M | G77: 0.016
A78: 03/23/2026 | B78: 2052.2 | C78: 2062.3 | D78: 2097 | E78: 2033.3 | F78: 2.60M | G78: -0.0146
A79: 03/20/2026 | B79: 2082.7 | C79: 2099.7 | D79: 2099.8 | E79: 2069 | F79: 2.43M | G79: 0.0026
A80: 03/19/2026 | B80: 2077.3 | C80: 2112 | D80: 2133.6 | E80: 2070.1 | F80: 2.10M | G80: -0.0272
A81: 03/18/2026 | B81: 2135.3 | C81: 2165 | D81: 2175 | E81: 2129.7 | F81: 2.44M | G81: -0.0106
A82: 03/17/2026 | B82: 2158.2 | C82: 2172.8 | D82: 2184.8 | E82: 2145.5 | F82: 1.71M | G82: -0.008
A83: 03/16/2026 | B83: 2175.7 | C83: 2169.6 | D83: 2186.7 | E83: 2154 | F83: 1.98M | G83: 0.0073
A84: 03/13/2026 | B84: 2160 | C84: 2136 | D84: 2191.9 | E84: 2120.3 | F84: 2.30M | G84: 0.0108
A85: 46359 | B85: 2136.9 | C85: 2165.1 | D85: 2165.1 | E85: 2109.3 | F85: 1.79M | G85: -0.0113
A86: 46329 | B86: 2161.4 | C86: 2190.2 | D86: 2195 | E86: 2156 | F86: 1.31M | G86: -0.0131
A87: 46298 | B87: 2190.2 | C87: 2224 | D87: 2224 | E87: 2175 | F87: 1.08M | G87: -0.002
A88: 46268 | B88: 2194.6 | C88: 2199 | D88: 2200 | E88: 2170.4 | F88: 1.51M | G88: -0.014
A89: 46176 | B89: 2225.7 | C89: 2245.1 | D89: 2250 | E89: 2219.5 | F89: 1.67M | G89: -0.013
A90: 46145 | B90: 2255 | C90: 2275.5 | D90: 2277.8 | E90: 2228.4 | F90: 1.75M | G90: -0.0028
A91: 46115 | B91: 2261.3 | C91: 2292.9 | D91: 2311.6 | E91: 2252.1 | F91: 2.65M | G91: -0.0256
A92: 46056 | B92: 2320.6 | C92: 2303 | D92: 2354 | E92: 2290.2 | F92: 2.27M | G92: -0.0075
A93: 02/27/2026 | B93: 2338.1 | C93: 2369.3 | D93: 2378.9 | E93: 2330.6 | F93: 3.05M | G93: -0.019
A94: 02/26/2026 | B94: 2383.3 | C94: 2378 | D94: 2387.3 | E94: 2355.2 | F94: 1.47M | G94: 0.0035
A95: 02/25/2026 | B95: 2374.9 | C95: 2368.9 | D95: 2380 | E95: 2349 | F95: 1.16M | G95: 0.0069
A96: 02/24/2026 | B96: 2358.6 | C96: 2331.1 | D96: 2372 | E96: 2330.3 | F96: 1.54M | G96: 0.0056
A97: 02/23/2026 | B97: 2345.4 | C97: 2325 | D97: 2350 | E97: 2320.8 | F97: 1.30M | G97: 0.0134
A98: 02/20/2026 | B98: 2314.5 | C98: 2285 | D98: 2331.2 | E98: 2278.3 | F98: 1.72M | G98: 0.0154
A99: 02/19/2026 | B99: 2279.3 | C99: 2336 | D99: 2337.4 | E99: 2275.6 | F99: 940.18K | G99: -0.019
A100: 02/18/2026 | B100: 2323.5 | C100: 2312.6 | D100: 2328.9 | E100: 2306 | F100: 830.79K | G100: 0.0048
...

Sheet Infosys
A1: Date | B1: Price | C1: Open | D1: High | E1: Low | F1: Vol. | G1: Change %
A2: 07/16/2026 | B2: 1082.4 | C2: 1082.5 | D2: 1097.3 | E2: 1077.9 | F2: 8.59M | G2: 0.0057
A3: 07/15/2026 | B3: 1076.3 | C3: 1079 | D3: 1088.1 | E3: 1073 | F3: 8.50M | G3: -0.0152
A4: 07/14/2026 | B4: 1092.9 | C4: 1107.8 | D4: 1113.5 | E4: 1090 | F4: 14.82M | G4: -0.0088
A5: 07/13/2026 | B5: 1102.6 | C5: 1057.1 | D5: 1114.9 | E5: 1057.1 | F5: 20.99M | G5: 0.0324
A6: 46302 | B6: 1068 | C6: 1075 | D6: 1091.3 | E6: 1064.7 | F6: 9.75M | G6: 0.0164
A7: 46272 | B7: 1050.8 | C7: 1062.7 | D7: 1062.7 | E7: 1040.4 | F7: 9.00M | G7: -0.0173
A8: 46241 | B8: 1069.3 | C8: 1071.9 | D8: 1079.7 | E8: 1064.4 | F8: 13.02M | G8: -0.0023
A9: 46210 | B9: 1071.8 | C9: 1040.6 | D9: 1087.5 | E9: 1040.6 | F9: 18.87M | G9: 0.0284
A10: 46180 | B10: 1042.2 | C10: 1050.1 | D10: 1053 | E10: 1033 | F10: 5.56M | G10: -0.0048
A11: 46088 | B11: 1047.2 | C11: 1063 | D11: 1068.7 | E11: 1042 | F11: 11.65M | G11: 0.0061
A12: 46060 | B12: 1040.9 | C12: 1006.4 | D12: 1045 | E12: 1006 | F12: 18.74M | G12: 0.0564
A13: 46029 | B13: 985.3 | C13: 1006 | D13: 1014 | E13: 982.4 | F13: 13.04M | G13: -0.0151
A14: 06/30/2026 | B14: 1000.4 | C14: 1030 | D14: 1030.4 | E14: 996 | F14: 24.13M | G14: -0.035
A15: 06/29/2026 | B15: 1036.7 | C15: 1037.1 | D15: 1046.6 | E15: 1029.1 | F15: 15.08M | G15: -0.0043
A16: 06/25/2026 | B16: 1041.2 | C16: 1065 | D16: 1068 | E16: 1039.1 | F16: 15.87M | G16: -0.0146
A17: 06/24/2026 | B17: 1056.6 | C17: 1040.9 | D17: 1065.5 | E17: 1037.7 | F17: 12.35M | G17: 0.0265
A18: 06/23/2026 | B18: 1029.3 | C18: 1053.8 | D18: 1055.3 | E18: 1026 | F18: 19.32M | G18: -0.0339
A19: 06/22/2026 | B19: 1065.4 | C19: 1055 | D19: 1080.3 | E19: 1055 | F19: 10.18M | G19: 0.0133
A20: 06/19/2026 | B20: 1051.4 | C20: 1062.3 | D20: 1066 | E20: 1030 | F20: 45.67M | G20: -0.0675
A21: 06/18/2026 | B21: 1127.5 | C21: 1142.9 | D21: 1142.9 | E21: 1125.3 | F21: 16.78M | G21: -0.0261
A22: 06/17/2026 | B22: 1157.7 | C22: 1149 | D22: 1162.5 | E22: 1148 | F22: 6.00M | G22: 0.0123
A23: 06/16/2026 | B23: 1143.6 | C23: 1136.9 | D23: 1153.8 | E23: 1123.2 | F23: 10.46M | G23: 0.0077
A24: 06/15/2026 | B24: 1134.9 | C24: 1130 | D24: 1151 | E24: 1123 | F24: 7.86M | G24: 0.0166
A25: 46362 | B25: 1116.4 | C25: 1120 | D25: 1123.3 | E25: 1111.5 | F25: 8.08M | G25: 0.0016
A26: 46332 | B26: 1114.6 | C26: 1129.7 | D26: 1133.7 | E26: 1109 | F26: 9.37M | G26: -0.0268
A27: 46301 | B27: 1145.3 | C27: 1160.1 | D27: 1171.4 | E27: 1143.3 | F27: 8.89M | G27: -0.0297
A28: 46271 | B28: 1180.3 | C28: 1193.6 | D28: 1193.6 | E28: 1167.3 | F28: 10.98M | G28: -0.0061
A29: 46240 | B29: 1187.6 | C29: 1177.5 | D29: 1200.7 | E29: 1176.5 | F29: 8.63M | G29: -0.0083
A30: 46148 | B30: 1197.5 | C30: 1220 | D30: 1223.8 | E30: 1194.3 | F30: 8.69M | G30: -0.0032
A31: 46118 | B31: 1201.3 | C31: 1208 | D31: 1215.2 | E31: 1196.2 | F31: 12.76M | G31: -0.0174
A32: 46087 | B32: 1222.6 | C32: 1242.1 | D32: 1249.9 | E32: 1216 | F32: 18.53M | G32: -0.0379
A33: 46059 | B33: 1270.8 | C33: 1232.5 | D33: 1278.9 | E33: 1232.5 | F33: 36.03M | G33: 0.0568
A34: 46028 | B34: 1202.5 | C34: 1175 | D34: 1217 | E34: 1173.7 | F34: 19.44M | G34: 0.0358
A35: 05/29/2026 | B35: 1160.9 | C35: 1182 | D35: 1210 | E35: 1153.6 | F35: 69.09M | G35: 0.0009
A36: 05/27/2026 | B36: 1159.9 | C36: 1161 | D36: 1167.3 | E36: 1155 | F36: 6.37M | G36: -0.0067
A37: 05/26/2026 | B37: 1167.7 | C37: 1166.3 | D37: 1180.7 | E37: 1162.9 | F37: 8.01M | G37: -0.0007
A38: 05/25/2026 | B38: 1168.5 | C38: 1183 | D38: 1185 | E38: 1166.1 | F38: 5.86M | G38: -0.0051
A39: 05/22/2026 | B39: 1174.5 | C39: 1182.5 | D39: 1191.8 | E39: 1172.5 | F39: 8.80M | G39: -0.0057
A40: 05/21/2026 | B40: 1181.2 | C40: 1196.1 | D40: 1201.8 | E40: 1177 | F40: 10.02M | G40: -0.0105
A41: 05/20/2026 | B41: 1193.7 | C41: 1187 | D41: 1206.9 | E41: 1184.9 | F41: 15.12M | G41: -0.0027
A42: 05/19/2026 | B42: 1196.9 | C42: 1162 | D42: 1198.4 | E42: 1162 | F42: 32.18M | G42: 0.0476
A43: 05/18/2026 | B43: 1142.5 | C43: 1119 | D43: 1146.1 | E43: 1118 | F43: 12.10M | G43: 0.021
A44: 05/15/2026 | B44: 1119 | C44: 1102 | D44: 1133.2 | E44: 1101.6 | F44: 17.48M | G44: 0.0219
A45: 05/14/2026 | B45: 1095 | C45: 1119.8 | D45: 1121.9 | E45: 1089 | F45: 16.91M | G45: -0.025
A46: 05/13/2026 | B46: 1123.1 | C46: 1136.6 | D46: 1142.6 | E46: 1121 | F46: 6.66M | G46: -0.0151
A47: 46361 | B47: 1140.3 | C47: 1162 | D47: 1162 | E47: 1123 | F47: 16.89M | G47: -0.0312
A48: 46331 | B48: 1177 | C48: 1176 | D48: 1187 | E48: 1172.1 | F48: 7.34M | G48: -0.0019
A49: 46239 | B49: 1179.2 | C49: 1161 | D49: 1183.5 | E49: 1158.8 | F49: 7.58M | G49: 0.0142
A50: 46208 | B50: 1162.7 | C50: 1173 | D50: 1175.4 | E50: 1159.2 | F50: 12.01M | G50: -0.0039
A51: 46178 | B51: 1167.2 | C51: 1187 | D51: 1191.5 | E51: 1164.1 | F51: 9.86M | G51: -0.0093
A52: 46147 | B52: 1178.1 | C52: 1169.5 | D52: 1185.2 | E52: 1160.1 | F52: 8.16M | G52: 0.0083
A53: 46117 | B53: 1168.4 | C53: 1195 | D53: 1195 | E53: 1165.2 | F53: 7.74M | G53: -0.0113
A54: 04/30/2026 | B54: 1181.8 | C54: 1167.5 | D54: 1189.8 | E54: 1159.6 | F54: 12.21M | G54: 0.0122
A55: 04/29/2026 | B55: 1167.5 | C55: 1158.5 | D55: 1178.2 | E55: 1156.8 | F55: 8.30M | G55: 0.0134
A56: 04/28/2026 | B56: 1152.1 | C56: 1162.7 | D56: 1169.4 | E56: 1149.8 | F56: 12.72M | G56: -0.0156
A57: 04/27/2026 | B57: 1170.3 | C57: 1154.6 | D57: 1179.9 | E57: 1154.5 | F57: 19.58M | G57: 0.0136
A58: 04/24/2026 | B58: 1154.6 | C58: 1200 | D58: 1223.9 | E58: 1152.2 | F58: 42.08M | G58: -0.0693
A59: 04/23/2026 | B59: 1240.6 | C59: 1254 | D59: 1265.7 | E59: 1226 | F59: 14.79M | G59: -0.0221
A60: 04/22/2026 | B60: 1268.6 | C60: 1295 | D60: 1297.7 | E60: 1255.9 | F60: 20.09M | G60: -0.034
A61: 04/21/2026 | B61: 1313.2 | C61: 1310 | D61: 1325 | E61: 1299.3 | F61: 10.06M | G61: 0.0005
A62: 04/20/2026 | B62: 1312.6 | C62: 1320 | D62: 1324.9 | E62: 1308.1 | F62: 7.17M | G62: -0.0046
A63: 04/17/2026 | B63: 1318.7 | C63: 1313 | D63: 1328.3 | E63: 1306.1 | F63: 12.06M | G63: -0.0004
A64: 04/16/2026 | B64: 1319.2 | C64: 1322.1 | D64: 1331 | E64: 1309 | F64: 18.53M | G64: 0.0106
A65: 04/15/2026 | B65: 1305.3 | C65: 1306.3 | D65: 1322.5 | E65: 1300.5 | F65: 12.10M | G65: 0.0223
A66: 04/13/2026 | B66: 1276.8 | C66: 1272 | D66: 1289 | E66: 1265.7 | F66: 10.37M | G66: -0.0121
A67: 46299 | B67: 1292.5 | C67: 1318 | D67: 1318.9 | E67: 1283.3 | F67: 19.23M | G67: -0.0294
A68: 46269 | B68: 1331.6 | C68: 1329.9 | D68: 1337.5 | E68: 1314 | F68: 14.89M | G68: -0.0108
A69: 46238 | B69: 1346.2 | C69: 1349 | D69: 1376.9 | E69: 1331 | F69: 16.03M | G69: 0.0051
A70: 46207 | B70: 1339.4 | C70: 1302 | D70: 1345.1 | E70: 1293.5 | F70: 15.36M | G70: 0.0254
A71: 46177 | B71: 1306.2 | C71: 1301.4 | D71: 1320 | E71: 1299 | F71: 10.21M | G71: 0.0042
A72: 46057 | B72: 1300.8 | C72: 1260 | D72: 1305.4 | E72: 1259.8 | F72: 12.87M | G72: 0.0197
A73: 46026 | B73: 1275.7 | C73: 1290 | D73: 1303 | E73: 1269.5 | F73: 8.14M | G73: 0.0201
A74: 03/30/2026 | B74: 1250.6 | C74: 1250 | D74: 1265.5 | E74: 1243 | F74: 14.11M | G74: -0.015
A75: 03/27/2026 | B75: 1269.7 | C75: 1285.2 | D75: 1294.8 | E75: 1263.2 | F75: 13.09M | G75: -0.0073
A76: 03/25/2026 | B76: 1279.1 | C76: 1270 | D76: 1290.6 | E76: 1257.1 | F76: 10.82M | G76: 0.0006
A77: 03/24/2026 | B77: 1278.3 | C77: 1269 | D77: 1297 | E77: 1251 | F77: 13.61M | G77: 0.0171
A78: 03/23/2026 | B78: 1256.8 | C78: 1238.2 | D78: 1261.1 | E78: 1227.4 | F78: 12.42M | G78: 0.0007
A79: 03/20/2026 | B79: 1255.9 | C79: 1242 | D79: 1264.8 | E79: 1229.2 | F79: 27.30M | G79: 0.0288
A80: 03/19/2026 | B80: 1220.8 | C80: 1244.2 | D80: 1255 | E80: 1215.1 | F80: 9.16M | G80: -0.0365
A81: 03/18/2026 | B81: 1267.1 | C81: 1238 | D81: 1290.8 | E81: 1234.9 | F81: 12.37M | G81: 0.0277
A82: 03/17/2026 | B82: 1232.9 | C82: 1245 | D82: 1245 | E82: 1215.1 | F82: 11.22M | G82: -0.0135
A83: 03/16/2026 | B83: 1249.8 | C83: 1240.2 | D83: 1254.3 | E83: 1224.2 | F83: 12.31M | G83: 0.0012
A84: 03/13/2026 | B84: 1248.3 | C84: 1251 | D84: 1269.6 | E84: 1242.6 | F84: 7.37M | G84: -0.0138
A85: 46359 | B85: 1265.8 | C85: 1272.5 | D85: 1278.6 | E85: 1258 | F85: 7.60M | G85: -0.0082
A86: 46329 | B86: 1276.3 | C86: 1288 | D86: 1299.5 | E86: 1271.3 | F86: 7.87M | G86: -0.0149
A87: 46298 | B87: 1295.6 | C87: 1320 | D87: 1321 | E87: 1284.1 | F87: 9.60M | G87: -0.0148
A88: 46268 | B88: 1315 | C88: 1290 | D88: 1318 | E88: 1282.5 | F88: 10.07M | G88: 0.005
A89: 46176 | B89: 1308.4 | C89: 1303 | D89: 1327.2 | E89: 1303 | F89: 8.72M | G89: 0.002
A90: 46145 | B90: 1305.8 | C90: 1320 | D90: 1320 | E90: 1290.1 | F90: 10.36M | G90: -0.0012
A91: 46115 | B91: 1307.4 | C91: 1292 | D91: 1317 | E91: 1292 | F91: 15.15M | G91: 0.0144
A92: 46056 | B92: 1288.9 | C92: 1291 | D92: 1298.8 | E92: 1273 | F92: 9.70M | G92: -0.0086
A93: 02/27/2026 | B93: 1300.1 | C93: 1326.3 | D93: 1335 | E93: 1294.2 | F93: 23.14M | G93: 0.0085
A94: 02/26/2026 | B94: 1289.1 | C94: 1305.5 | D94: 1314 | E94: 1286.3 | F94: 11.49M | G94: -0.0008
A95: 02/25/2026 | B95: 1290.1 | C95: 1286.2 | D95: 1323.6 | E95: 1286.2 | F95: 16.67M | G95: 0.0114
A96: 02/24/2026 | B96: 1275.5 | C96: 1301 | D96: 1303.6 | E96: 1264.1 | F96: 27.84M | G96: -0.0392
A97: 02/23/2026 | B97: 1327.5 | C97: 1352 | D97: 1352 | E97: 1318 | F97: 12.89M | G97: -0.019
A98: 02/20/2026 | B98: 1353.2 | C98: 1359.2 | D98: 1365 | E98: 1338.2 | F98: 12.63M | G98: -0.0126
A99: 02/19/2026 | B99: 1370.5 | C99: 1385 | D99: 1402 | E99: 1363.2 | F99: 14.57M | G99: -0.0023
A100: 02/18/2026 | B100: 1373.7 | C100: 1390.9 | D100: 1401 | E100: 1345.3 | F100: 20.24M | G100: -0.0126
...

Sheet HDFC Bank
A1: Date | B1: Price | C1: Open | D1: High | E1: Low | F1: Vol. | G1: Change %
A2: 07/16/2026 | B2: 808.3 | C2: 814.5 | D2: 818 | E2: 806.5 | F2: 18.70M | G2: -0.0088
A3: 07/15/2026 | B3: 815.45 | C3: 811 | D3: 819.7 | E3: 809.7 | F3: 21.49M | G3: 0.0075
A4: 07/14/2026 | B4: 809.4 | C4: 811.4 | D4: 818.4 | E4: 807 | F4: 25.61M | G4: -0.0105
A5: 07/13/2026 | B5: 817.95 | C5: 817 | D5: 821.95 | E5: 811 | F5: 21.74M | G5: -0.0085
A6: 46302 | B6: 824.95 | C6: 824 | D6: 827.7 | E6: 820.3 | F6: 23.60M | G6: 0.0091
A7: 46272 | B7: 817.55 | C7: 813 | D7: 822.85 | E7: 812.3 | F7: 39.89M | G7: 0.0089
A8: 46241 | B8: 810.3 | C8: 825.9 | D8: 834.35 | E8: 806.95 | F8: 38.75M | G8: -0.0229
A9: 46210 | B9: 829.3 | C9: 843 | D9: 843 | E9: 826.1 | F9: 57.61M | G9: -0.0007
A10: 46180 | B10: 829.85 | C10: 805 | D10: 831.5 | E10: 805 | F10: 63.20M | G10: 0.036
A11: 46088 | B11: 801.05 | C11: 803 | D11: 807 | E11: 798.55 | F11: 25.87M | G11: 0.0065
A12: 46060 | B12: 795.9 | C12: 795 | D12: 805.45 | E12: 794 | F12: 34.14M | G12: -0.0003
A13: 46029 | B13: 796.15 | C13: 793.5 | D13: 802.25 | E13: 793.5 | F13: 26.09M | G13: -0.0023
A14: 06/30/2026 | B14: 797.95 | C14: 806.1 | D14: 806.1 | E14: 792.75 | F14: 45.78M | G14: -0.0012
A15: 06/29/2026 | B15: 798.9 | C15: 800 | D15: 805.9 | E15: 793.3 | F15: 46.70M | G15: 0.0033
A16: 06/25/2026 | B16: 796.3 | C16: 798.5 | D16: 804.45 | E16: 794.75 | F16: 46.71M | G16: 0.0039
A17: 06/24/2026 | B17: 793.2 | C17: 773 | D17: 794.9 | E17: 772.65 | F17: 34.70M | G17: 0.0239
A18: 06/23/2026 | B18: 774.65 | C18: 783.05 | D18: 790.9 | E18: 772.55 | F18: 28.29M | G18: -0.0149
A19: 06/22/2026 | B19: 786.4 | C19: 789.9 | D19: 789.9 | E19: 783.1 | F19: 25.19M | G19: 0.0085
A20: 06/19/2026 | B20: 779.8 | C20: 788.7 | D20: 789.05 | E20: 776.2 | F20: 33.80M | G20: -0.024
A21: 06/18/2026 | B21: 799 | C21: 786.5 | D21: 802.95 | E21: 786.2 | F21: 41.49M | G21: 0.0151
A22: 06/17/2026 | B22: 787.1 | C22: 787.65 | D22: 794.3 | E22: 783.1 | F22: 32.41M | G22: 0.0028
A23: 06/16/2026 | B23: 784.9 | C23: 780.5 | D23: 787.7 | E23: 779.45 | F23: 27.82M | G23: 0.0097
A24: 06/15/2026 | B24: 777.35 | C24: 790 | D24: 793.5 | E24: 775.6 | F24: 39.99M | G24: 0.0063
A25: 46362 | B25: 772.45 | C25: 754.7 | D25: 774.45 | E25: 753.1 | F25: 36.09M | G25: 0.0374
A26: 46332 | B26: 744.6 | C26: 743 | D26: 756 | E26: 740.1 | F26: 32.63M | G26: -0.003
A27: 46301 | B27: 746.85 | C27: 736.5 | D27: 755.95 | E27: 736.4 | F27: 44.46M | G27: 0.0115
A28: 46271 | B28: 738.35 | C28: 739.45 | D28: 743.95 | E28: 732.3 | F28: 38.54M | G28: -0.0004
A29: 46240 | B29: 738.65 | C29: 738 | D29: 741.5 | E29: 734.5 | F29: 21.55M | G29: -0.0112
A30: 46148 | B30: 747.05 | C30: 753.95 | D30: 758.7 | E30: 744.65 | F30: 22.12M | G30: -0.0095
A31: 46118 | B31: 754.2 | C31: 749.15 | D31: 757.3 | E31: 745 | F31: 42.67M | G31: 0.0007
A32: 46087 | B32: 753.65 | C32: 744.45 | D32: 756.9 | E32: 742.6 | F32: 36.11M | G32: 0.0072
A33: 46059 | B33: 748.25 | C33: 737 | D33: 753.6 | E33: 733.15 | F33: 47.31M | G33: 0.0075
A34: 46028 | B34: 742.7 | C34: 749 | D34: 752.35 | E34: 739.2 | F34: 48.00M | G34: -0.0025
A35: 05/29/2026 | B35: 744.55 | C35: 746.05 | D35: 760.5 | E35: 737.75 | F35: 101.30M | G35: -0.0186
A36: 05/27/2026 | B36: 758.65 | C36: 769.5 | D36: 773.9 | E36: 756.9 | F36: 63.68M | G36: -0.026
A37: 05/26/2026 | B37: 778.9 | C37: 784.05 | D37: 790.85 | E37: 776.75 | F37: 31.53M | G37: -0.0101
A38: 05/25/2026 | B38: 786.85 | C38: 776 | D38: 787.85 | E38: 775.2 | F38: 26.04M | G38: 0.0261
A39: 05/22/2026 | B39: 766.8 | C39: 759.15 | D39: 775 | E39: 759.15 | F39: 25.60M | G39: 0.0101
A40: 05/21/2026 | B40: 759.15 | C40: 767 | D40: 768.25 | E40: 755.15 | F40: 34.66M | G40: -0.0005
A41: 05/20/2026 | B41: 759.5 | C41: 759.6 | D41: 762.25 | E41: 755.15 | F41: 24.01M | G41: -0.0039
A42: 05/19/2026 | B42: 762.45 | C42: 766.7 | D42: 770.8 | E42: 760.25 | F42: 40.31M | G42: -0.0081
A43: 05/18/2026 | B43: 768.65 | C43: 759 | D43: 774.1 | E43: 751.35 | F43: 29.81M | G43: 0.0015
A44: 05/15/2026 | B44: 767.5 | C44: 773 | D44: 781.9 | E44: 765.4 | F44: 24.35M | G44: -0.0027
A45: 05/14/2026 | B45: 769.55 | C45: 751 | D45: 778.3 | E45: 747 | F45: 50.99M | G45: 0.0266
A46: 05/13/2026 | B46: 749.6 | C46: 752 | D46: 759.95 | E46: 747.35 | F46: 28.96M | G46: -0.0011
A47: 46361 | B47: 750.45 | C47: 756.6 | D47: 759.7 | E47: 747.8 | F47: 43.94M | G47: -0.0173
A48: 46331 | B48: 763.65 | C48: 771.95 | D48: 774.85 | E48: 761.9 | F48: 41.12M | G48: -0.022
A49: 46239 | B49: 780.85 | C49: 784 | D49: 788.75 | E49: 777.2 | F49: 38.02M | G49: -0.0191
A50: 46208 | B50: 796.05 | C50: 794 | D50: 801.55 | E50: 788.55 | F50: 46.14M | G50: -0.0006
A51: 46178 | B51: 796.55 | C51: 775.15 | D51: 798.95 | E51: 773.5 | F51: 35.53M | G51: 0.0314
A52: 46147 | B52: 772.3 | C52: 774.4 | D52: 776.9 | E52: 763.7 | F52: 38.89M | G52: -0.0091
A53: 46117 | B53: 779.4 | C53: 772.6 | D53: 786.6 | E53: 772.6 | F53: 29.03M | G53: 0.01
A54: 04/30/2026 | B54: 771.7 | C54: 770 | D54: 778.8 | E54: 762.25 | F54: 48.00M | G54: -0.0094
A55: 04/29/2026 | B55: 779 | C55: 785.5 | D55: 790 | E55: 777.35 | F55: 25.80M | G55: -0.0045
A56: 04/28/2026 | B56: 782.55 | C56: 785 | D56: 794.5 | E56: 778.3 | F56: 35.37M | G56: -0.0092
A57: 04/27/2026 | B57: 789.8 | C57: 787.5 | D57: 793 | E57: 785 | F57: 18.12M | G57: 0.0063
A58: 04/24/2026 | B58: 784.85 | C58: 777.3 | D58: 787.6 | E58: 777 | F58: 27.72M | G58: 0.0006
A59: 04/23/2026 | B59: 784.35 | C59: 792 | D59: 796.65 | E59: 782.5 | F59: 37.68M | G59: -0.0194
A60: 04/22/2026 | B60: 799.9 | C60: 810 | D60: 813.05 | E60: 798 | F60: 23.88M | G60: -0.0146
A61: 04/21/2026 | B61: 811.75 | C61: 795.2 | D61: 814.9 | E61: 795.2 | F61: 49.14M | G61: 0.0205
A62: 04/20/2026 | B62: 795.45 | C62: 797.1 | D62: 809.95 | E62: 790 | F62: 52.15M | G62: -0.0056
A63: 04/17/2026 | B63: 799.9 | C63: 790.1 | D63: 803.95 | E63: 788.2 | F63: 37.28M | G63: 0.0056
A64: 04/16/2026 | B64: 795.45 | C64: 818 | D64: 820.05 | E64: 792.2 | F64: 62.86M | G64: -0.0178
A65: 04/15/2026 | B65: 809.9 | C65: 804.95 | D65: 814.8 | E65: 804 | F65: 39.77M | G65: 0.0191
A66: 04/13/2026 | B66: 794.7 | C66: 791.5 | D66: 798.5 | E66: 787.35 | F66: 47.55M | G66: -0.0193
A67: 46299 | B67: 810.3 | C67: 804 | D67: 812.25 | E67: 801 | F67: 38.16M | G67: 0.0158
A68: 46269 | B68: 797.7 | C68: 815 | D68: 819 | E68: 793.1 | F68: 48.88M | G68: -0.0225
A69: 46238 | B69: 816.1 | C69: 800 | D69: 817.8 | E69: 796 | F69: 70.27M | G69: 0.0571
A70: 46207 | B70: 772 | C70: 766 | D70: 774 | E70: 761 | F70: 51.31M | G70: 0.0013
A71: 46177 | B71: 771 | C71: 759 | D71: 772.75 | E71: 745 | F71: 42.98M | G71: 0.0268
A72: 46057 | B72: 750.9 | C72: 730 | D72: 755 | E72: 726.65 | F72: 49.31M | G72: 0.0117
A73: 46026 | B73: 742.25 | C73: 743 | D73: 755.9 | E73: 739.1 | F73: 78.86M | G73: 0.0146
A74: 03/30/2026 | B74: 731.55 | C74: 745.2 | D74: 751 | E74: 726.65 | F74: 103.50M | G74: -0.0326
A75: 03/27/2026 | B75: 756.2 | C75: 773.2 | D75: 774.9 | E75: 754.55 | F75: 65.49M | G75: -0.0334
A76: 03/25/2026 | B76: 782.3 | C76: 768.2 | D76: 794.8 | E76: 768.2 | F76: 59.23M | G76: 0.0227
A77: 03/24/2026 | B77: 764.9 | C77: 755 | D77: 772.75 | E77: 747.7 | F77: 61.27M | G77: 0.0279
A78: 03/23/2026 | B78: 744.15 | C78: 763.15 | D78: 768.7 | E78: 741.05 | F78: 72.34M | G78: -0.0465
A79: 03/20/2026 | B79: 780.45 | C79: 785 | D79: 793.75 | E79: 778.2 | F79: 103.13M | G79: -0.0222
A80: 03/19/2026 | B80: 798.2 | C80: 770 | D80: 815.65 | E80: 770 | F80: 171.64M | G80: -0.0532
A81: 03/18/2026 | B81: 843.05 | C81: 845.35 | D81: 846.8 | E81: 831.6 | F81: 23.51M | G81: -0.0027
A82: 03/17/2026 | B82: 845.35 | C82: 847.7 | D82: 848.9 | E82: 835.1 | F82: 38.83M | G82: 0.0057
A83: 03/16/2026 | B83: 840.6 | C83: 817 | D83: 844.5 | E83: 815.65 | F83: 52.18M | G83: 0.0289
A84: 03/13/2026 | B84: 817 | C84: 820 | D84: 823.8 | E84: 812 | F84: 41.70M | G84: -0.0189
A85: 46359 | B85: 832.75 | C85: 820.1 | D85: 836.4 | E85: 820.1 | F85: 46.11M | G85: -0.0014
A86: 46329 | B86: 833.95 | C86: 845 | D86: 848.85 | E86: 827.6 | F86: 42.26M | G86: -0.0182
A87: 46298 | B87: 849.45 | C87: 850.05 | D87: 856.8 | E87: 840.6 | F87: 52.87M | G87: 0.0104
A88: 46268 | B88: 840.7 | C88: 825 | D88: 842.45 | E88: 821.5 | F88: 35.59M | G88: -0.0191
A89: 46176 | B89: 857.05 | C89: 868.05 | D89: 871.7 | E89: 855.1 | F89: 34.44M | G89: -0.0236
A90: 46145 | B90: 877.75 | C90: 873.85 | D90: 881.4 | E90: 863.5 | F90: 31.32M | G90: 0.0105
A91: 46115 | B91: 868.65 | C91: 848 | D91: 879.3 | E91: 848 | F91: 39.86M | G91: -0.0122
A92: 46056 | B92: 879.4 | C92: 876.2 | D92: 887.75 | E92: 871.55 | F92: 38.38M | G92: -0.0094
A93: 02/27/2026 | B93: 887.75 | C93: 898.6 | D93: 898.95 | E93: 885 | F93: 34.62M | G93: -0.0121
A94: 02/26/2026 | B94: 898.6 | C94: 912 | D94: 912 | E94: 895 | F94: 41.17M | G94: -0.0099
A95: 02/25/2026 | B95: 907.6 | C95: 910.55 | D95: 916 | E95: 903.1 | F95: 27.88M | G95: -0.0032
A96: 02/24/2026 | B96: 910.5 | C96: 927.95 | D96: 927.95 | E96: 909.15 | F96: 31.31M | G96: -0.0142
A97: 02/23/2026 | B97: 923.6 | C97: 916.5 | D97: 925.65 | E97: 915.25 | F97: 23.27M | G97: 0.0129
A98: 02/20/2026 | B98: 911.85 | C98: 911 | D98: 917.85 | E98: 908.4 | F98: 22.65M | G98: -0.0041
A99: 02/19/2026 | B99: 915.6 | C99: 929 | D99: 929.2 | E99: 912.45 | F99: 21.21M | G99: -0.0098
A100: 02/18/2026 | B100: 924.7 | C100: 923.2 | D100: 925.5 | E100: 919.55 | F100: 12.74M | G100: -0.0011
...

Sheet Nifty 50
A1: Date | B1: Price | C1: Open | D1: High | E1: Low | F1: Vol. | G1: Change %
A2: 07/16/2026 | B2: 24072.75 | C2: 24142.1 | D2: 24185.9 | E2: 24052.35 | F2: 264.27M | G2: -0.0002
A3: 07/15/2026 | B3: 24078.5 | C3: 24085.85 | D3: 24220.35 | E3: 24010.55 | F3: 306.92M | G3: 0.0011
A4: 07/14/2026 | B4: 24052.05 | C4: 24068 | D4: 24157.1 | E4: 24023.7 | F4: 355.83M | G4: -0.0066
A5: 07/13/2026 | B5: 24211 | C5: 24039.4 | D5: 24259.8 | E5: 24000.2 | F5: 322.68M | G5: 0.0002
A6: 46302 | B6: 24206.9 | C6: 24124.7 | D6: 24228.45 | E6: 24120.35 | F6: 313.07M | G6: 0.0102
A7: 46272 | B7: 23962.8 | C7: 23928.95 | D7: 24134.7 | E7: 23925.7 | F7: 384.80M | G7: 0.0034
A8: 46241 | B8: 23882.05 | C8: 24259.55 | D8: 24300 | E8: 23805.2 | F8: 420.53M | G8: -0.0212
A9: 46210 | B9: 24398.7 | C9: 24464.45 | D9: 24530.9 | E9: 24348.95 | F9: 412.62M | G9: -0.0013
A10: 46180 | B10: 24430.35 | C10: 24306.85 | D10: 24458.65 | E10: 24287.1 | F10: 329.36M | G10: 0.0066
A11: 46088 | B11: 24270.85 | C11: 24375.65 | D11: 24378.15 | E11: 24252.35 | F11: 326.63M | G11: 0.0039
A12: 46060 | B12: 24175.7 | C12: 24062.2 | D12: 24194.55 | E12: 24058.8 | F12: 372.94M | G12: 0.0071
A13: 46029 | B13: 24005.85 | C13: 23897.65 | D13: 24049.9 | E13: 23895.1 | F13: 352.15M | G13: 0.0059
A14: 06/30/2026 | B14: 23865.75 | C14: 24032.05 | D14: 24035.55 | E14: 23829.2 | F14: 449.04M | G14: -0.0034
A15: 06/29/2026 | B15: 23946.25 | C15: 24061.75 | D15: 24120 | E15: 23924.55 | F15: 588.50M | G15: -0.0046
A16: 06/25/2026 | B16: 24056 | C16: 24125.85 | D16: 24261.6 | E16: 24039 | F16: 448.75M | G16: 0.0014
A17: 06/24/2026 | B17: 24021.65 | C17: 23795.8 | D17: 24090.05 | E17: 23789.25 | F17: 395.58M | G17: 0.0083
A18: 06/23/2026 | B18: 23824.1 | C18: 24071.3 | D18: 24135.5 | E18: 23784.95 | F18: 340.09M | G18: -0.0116
A19: 06/22/2026 | B19: 24102.9 | C19: 24106.6 | D19: 24168.05 | E19: 24073.15 | F19: 252.82M | G19: 0.0037
A20: 06/19/2026 | B20: 24013.1 | C20: 23991.2 | D20: 24047.2 | E20: 23901.9 | F20: 447.86M | G20: -0.0064
A21: 06/18/2026 | B21: 24168 | C21: 24073.8 | D21: 24189.25 | E21: 24036.95 | F21: 339.99M | G21: 0.0034
A22: 06/17/2026 | B22: 24085.7 | C22: 24044.5 | D22: 24108.2 | E22: 23969.7 | F22: 352.67M | G22: 0.004
A23: 06/16/2026 | B23: 23989.15 | C23: 23923.9 | D23: 24002.6 | E23: 23888.2 | F23: 327.31M | G23: 0.0057
A24: 06/15/2026 | B24: 23853.9 | C24: 23984.85 | D24: 24011.4 | E24: 23817.8 | F24: 398.91M | G24: 0.0098
A25: 46362 | B25: 23622.9 | C25: 23412.55 | D25: 23645.35 | E25: 23313.9 | F25: 351.94M | G25: 0.0199
A26: 46332 | B26: 23161.6 | C26: 23104.4 | D26: 23327.45 | E26: 23072.05 | F26: 363.00M | G26: -0.0023
A27: 46301 | B27: 23214.95 | C27: 23233.95 | D27: 23425.35 | E27: 23184.6 | F27: 380.03M | G27: -0.0012
A28: 46271 | B28: 23242.1 | C28: 23259.05 | D28: 23279.4 | E28: 23104.45 | F28: 402.55M | G28: 0.0052
A29: 46240 | B29: 23123 | C29: 23080.7 | D29: 23267.3 | E29: 23070.15 | F29: 375.73M | G29: -0.0104
A30: 46148 | B30: 23366.7 | C30: 23478.95 | D30: 23516.35 | E30: 23282.65 | F30: 366.21M | G30: -0.0021
A31: 46118 | B31: 23416.55 | C31: 23282.45 | D31: 23465.3 | E31: 23247.3 | F31: 412.51M | G31: 0.0005
A32: 46087 | B32: 23405.6 | C32: 23415.95 | D32: 23459.65 | E32: 23151.5 | F32: 450.08M | G32: -0.0033
A33: 46059 | B33: 23483.55 | C33: 23229.15 | D33: 23556.95 | E33: 23229.15 | F33: 511.85M | G33: 0.0043
A34: 46028 | B34: 23382.6 | C34: 23654.5 | D34: 23733.7 | E34: 23357.95 | F34: 421.69M | G34: -0.007
A35: 05/29/2026 | B35: 23547.75 | C35: 23902.15 | D35: 24002.8 | E35: 23484.75 | F35: 1.20B | G35: -0.015
A36: 05/27/2026 | B36: 23907.15 | C36: 23880.35 | D36: 23983.2 | E36: 23858.25 | F36: 531.57M | G36: -0.0003
A37: 05/26/2026 | B37: 23913.7 | C37: 24004.1 | D37: 24089.8 | E37: 23885.45 | F37: 387.93M | G37: -0.0049
A38: 05/25/2026 | B38: 24031.7 | C38: 23940.25 | D38: 24054.45 | E38: 23922.85 | F38: 351.22M | G38: 0.0132
A39: 05/22/2026 | B39: 23719.3 | C39: 23671.2 | D39: 23835.65 | E39: 23671 | F39: 336.11M | G39: 0.0027
A40: 05/21/2026 | B40: 23654.7 | C40: 23830.05 | D40: 23859.9 | E40: 23596.6 | F40: 348.18M | G40: -0.0002
A41: 05/20/2026 | B41: 23659 | C41: 23457.25 | D41: 23690.9 | E41: 23397.3 | F41: 344.05M | G41: 0.0017
A42: 05/19/2026 | B42: 23618 | C42: 23675.3 | D42: 23782.3 | E42: 23587.2 | F42: 441.95M | G42: -0.0014
A43: 05/18/2026 | B43: 23649.95 | C43: 23482.2 | D43: 23695.65 | E43: 23317.1 | F43: 391.97M | G43: 0.0003
A44: 05/15/2026 | B44: 23643.5 | C44: 23731.4 | D44: 23839.3 | E44: 23610.3 | F44: 408.86M | G44: -0.0019
A45: 05/14/2026 | B45: 23689.6 | C45: 23530.25 | D45: 23777.2 | E45: 23426.55 | F45: 428.74M | G45: 0.0118
A46: 05/13/2026 | B46: 23412.6 | C46: 23362.45 | D46: 23582.95 | E46: 23262.55 | F46: 415.36M | G46: 0.0014
A47: 46361 | B47: 23379.55 | C47: 23722.6 | D47: 23757.55 | E47: 23348.4 | F47: 447.52M | G47: -0.0183
A48: 46331 | B48: 23815.85 | C48: 23970.1 | D48: 23997.45 | E48: 23799.1 | F48: 390.11M | G48: -0.0149
A49: 46239 | B49: 24176.15 | C49: 24233.65 | D49: 24253.8 | E49: 24126.65 | F49: 335.89M | G49: -0.0062
A50: 46208 | B50: 24326.65 | C50: 24398.5 | D50: 24482.1 | E50: 24284 | F50: 440.62M | G50: -0.0002
A51: 46178 | B51: 24330.95 | C51: 24171 | D51: 24356.5 | E51: 23997.9 | F51: 429.19M | G51: 0.0124
A52: 46147 | B52: 24032.8 | C52: 24052.6 | D52: 24081.7 | E52: 23882.05 | F52: 363.30M | G52: -0.0036
A53: 46117 | B53: 24119.3 | C53: 24063.55 | D53: 24290.2 | E53: 24004.75 | F53: 419.07M | G53: 0.0051
A54: 04/30/2026 | B54: 23997.55 | C54: 23996.95 | D54: 24087.45 | E54: 23796.85 | F54: 505.52M | G54: -0.0074
A55: 04/29/2026 | B55: 24177.65 | C55: 24096.9 | D55: 24334.7 | E55: 24059.95 | F55: 531.12M | G55: 0.0076
A56: 04/28/2026 | B56: 23995.7 | C56: 24049.9 | D56: 24181.8 | E56: 23957.05 | F56: 554.13M | G56: -0.004
A57: 04/27/2026 | B57: 24092.7 | C57: 23945.45 | D57: 24130.7 | E57: 23936.2 | F57: 430.30M | G57: 0.0081
A58: 04/24/2026 | B58: 23897.95 | C58: 24100.55 | D58: 24206 | E58: 23813.65 | F58: 438.43M | G58: -0.0114
A59: 04/23/2026 | B59: 24173.05 | C59: 24202.35 | D59: 24310.2 | E59: 24134.8 | F59: 467.55M | G59: -0.0084
A60: 04/22/2026 | B60: 24378.1 | C60: 24470.85 | D60: 24515.95 | E60: 24352.9 | F60: 440.52M | G60: -0.0081
A61: 04/21/2026 | B61: 24576.6 | C61: 24374.55 | D61: 24601.7 | E61: 24354.9 | F61: 425.83M | G61: 0.0087
A62: 04/20/2026 | B62: 24364.85 | C62: 24391.5 | D62: 24480.65 | E62: 24241.25 | F62: 415.94M | G62: 0.0005
A63: 04/17/2026 | B63: 24353.55 | C63: 24165.9 | D63: 24371.9 | E63: 24096.05 | F63: 498.63M | G63: 0.0065
A64: 04/16/2026 | B64: 24196.75 | C64: 24385.2 | D64: 24400.95 | E64: 24102.8 | F64: 508.02M | G64: -0.0014
A65: 04/15/2026 | B65: 24231.3 | C65: 24163.8 | D65: 24280.9 | E65: 24145.8 | F65: 460.33M | G65: 0.0163
A66: 04/13/2026 | B66: 23842.65 | C66: 23589.6 | D66: 23907.4 | E66: 23555.6 | F66: 488.84M | G66: -0.0086
A67: 46299 | B67: 24050.6 | C67: 23880.55 | D67: 24074.05 | E67: 23856.35 | F67: 481.30M | G67: 0.0116
A68: 46269 | B68: 23775.1 | C68: 23909.05 | D68: 23990.75 | E68: 23682.8 | F68: 466.59M | G68: -0.0093
A69: 46238 | B69: 23997.35 | C69: 23855.15 | D69: 24025.15 | E69: 23828.5 | F69: 639.26M | G69: 0.0378
A70: 46207 | B70: 23123.65 | C70: 22838.7 | D70: 23153.85 | E70: 22719.3 | F70: 476.98M | G70: 0.0068
A71: 46177 | B71: 22968.25 | C71: 22780.3 | D71: 22998.35 | E71: 22542.95 | F71: 426.42M | G71: 0.0112
A72: 46057 | B72: 22713.1 | C72: 22383.4 | D72: 22782.3 | E72: 22182.55 | F72: 495.12M | G72: 0.0015
A73: 46026 | B73: 22679.4 | C73: 22899 | D73: 22941.3 | E73: 22618.6 | F73: 517.95M | G73: 0.0156
A74: 03/30/2026 | B74: 22331.4 | C74: 22549.65 | D74: 22714.1 | E74: 22283.85 | F74: 698.60M | G74: -0.0214
A75: 03/27/2026 | B75: 22819.6 | C75: 23173.55 | D75: 23186.1 | E75: 22804.55 | F75: 612.56M | G75: -0.0209
A76: 03/25/2026 | B76: 23306.45 | C76: 23064.4 | D76: 23465.35 | E76: 23063.2 | F76: 505.42M | G76: 0.0172
A77: 03/24/2026 | B77: 22912.4 | C77: 22878.45 | D77: 23057.3 | E77: 22624.2 | F77: 538.10M | G77: 0.0178
A78: 03/23/2026 | B78: 22512.65 | C78: 22824.35 | D78: 22851.7 | E78: 22471.25 | F78: 550.28M | G78: -0.026
A79: 03/20/2026 | B79: 23114.5 | C79: 23110.15 | D79: 23345.15 | E79: 23067.6 | F79: 663.29M | G79: 0.0049
A80: 03/19/2026 | B80: 23002.15 | C80: 23197.75 | D80: 23378.7 | E80: 22930.35 | F80: 550.15M | G80: -0.0326
A81: 03/18/2026 | B81: 23777.8 | C81: 23632.9 | D81: 23862.25 | E81: 23618.45 | F81: 382.88M | G81: 0.0083
A82: 03/17/2026 | B82: 23581.15 | C82: 23493.2 | D82: 23656.8 | E82: 23346.6 | F82: 458.79M | G82: 0.0074
A83: 03/16/2026 | B83: 23408.8 | C83: 23116.1 | D83: 23502 | E83: 22955.25 | F83: 540.29M | G83: 0.0111
A84: 03/13/2026 | B84: 23151.1 | C84: 23462.5 | D84: 23492.4 | E84: 23112 | F84: 519.78M | G84: -0.0206
A85: 46359 | B85: 23639.15 | C85: 23674.85 | D85: 23833.15 | E85: 23556.3 | F85: 501.00M | G85: -0.0095
A86: 46329 | B86: 23866.85 | C86: 24231.85 | D86: 24299 | E86: 23834.3 | F86: 407.40M | G86: -0.0163
A87: 46298 | B87: 24261.6 | C87: 24280.8 | D87: 24303.8 | E87: 24079.95 | F87: 444.28M | G87: 0.0097
A88: 46268 | B88: 24028.05 | C88: 23868.05 | D88: 24078.15 | E88: 23697.8 | F88: 526.90M | G88: -0.0173
A89: 46176 | B89: 24450.45 | C89: 24656.4 | D89: 24700.9 | E89: 24415.75 | F89: 433.41M | G89: -0.0127
A90: 46145 | B90: 24765.9 | C90: 24615.95 | D90: 24854.2 | E90: 24529.4 | F90: 504.34M | G90: 0.0117
A91: 46115 | B91: 24480.5 | C91: 24388.8 | D91: 24602.45 | E91: 24305.4 | F91: 598.99M | G91: -0.0155
A92: 46056 | B92: 24865.7 | C92: 24659.25 | D92: 24989.35 | E92: 24603.5 | F92: 519.23M | G92: -0.0124
A93: 02/27/2026 | B93: 25178.65 | C93: 25459.85 | D93: 25476.4 | E93: 25141.3 | F93: 438.92M | G93: -0.0125
A94: 02/26/2026 | B94: 25496.55 | C94: 25556.3 | D94: 25572.95 | E94: 25400.95 | F94: 405.22M | G94: 0.0006
A95: 02/25/2026 | B95: 25482.5 | C95: 25512.6 | D95: 25652.6 | E95: 25428.2 | F95: 414.21M | G95: 0.0023
A96: 02/24/2026 | B96: 25424.65 | C96: 25641.8 | D96: 25641.8 | E96: 25327.6 | F96: 439.07M | G96: -0.0112
A97: 02/23/2026 | B97: 25713 | C97: 25678.4 | D97: 25771.45 | E97: 25609.35 | F97: 313.68M | G97: 0.0055
A98: 02/20/2026 | B98: 25571.25 | C98: 25406.55 | D98: 25663.55 | E98: 25379.75 | F98: 296.58M | G98: 0.0046
A99: 02/19/2026 | B99: 25454.35 | C99: 25873.35 | D99: 25885.3 | E99: 25388.75 | F99: 298.23M | G99: -0.0141
A100: 02/18/2026 | B100: 25819.35 | C100: 25752.65 | D100: 25828.05 | E100: 25645.15 | F100: 310.23M | G100: 0.0037
...
